Workbook

Sheet DASHBOARD
B1: RELATÓRIO MENSAL | ABRIL/2026
B5: PROCESSOS ATIVOS | E5: EXPOSIÇÃO TOTAL | J5: PROCESSOS ENCERRADOS | O5: TAXA DE ÊXITO
B6: =COUNTIF('Relatório - Processos Ativos'!F2:F100,"<>") -> 1 | E6: {=IFERROR(SUMPRODUCT(NUMBERVALUE(SUBSTITUTE('Relatório - Processos Ativos'!Z2:Z100,"R$ ",""),",",".")*('Relatório - Processos Ativos'!F2:F100<>"")),0)} -> 0 | J6: =COUNTIF('Processos arquivados'!B2:B100,"<>") -> 3 | O6: =(COUNTIF('Processos arquivados'!V2:V100,"ACORDO*")+COUNTIF('Processos arquivados'!U2:U100,"*improceden*"))/COUNTIF('Processos arquivados'!B2:B100,"<>") -> 1
B7: em andamento | E7: valor da causa | J7: no período | O7: casos favoráveis
B9: ▎ ANÁLISE DE RISCO DOS PROCESSOS ATIVOS | J9: ▎ DISTRIBUIÇÃO POR RISCO
B10: PROCESSO | C10: RECLAMANTE | D10: VALOR (R$) | E10: RISCO | F10: FASE ATUAL | J10: CLASSIFICAÇÃO | K10: QTD | L10: VALOR (R$) | M10: % DO TOTAL
B11: ='Relatório - Processos Ativos'!F2 -> 0010526-41.2024.5.15.0002 | C11: ='Relatório - Processos Ativos'!D2 -> ADRIANO SOARES DE LIMA | D11: ='Relatório - Processos Ativos'!Z2 -> R$ 110.248,73 | E11: ='Relatório - Processos Ativos'!AA2 -> PROVÁVEL | F11: ='Relatório - Processos Ativos'!AG2 -> RECURSAL | J11: ● PROVÁVEL | K11: =COUNTIF('Relatório - Processos Ativos'!AA2:AA100,"PROVÁVEL") -> 1 | L11: {=IFERROR(SUMPRODUCT(NUMBERVALUE(SUBSTITUTE('Relatório - Processos Ativos'!Z2:Z100,"R$ ",""),",",".")*('Relatório - Processos Ativos'!AA2:AA100="PROVÁVEL")),0)} -> 0 | M11: =IF(K14=0,0,K11/K14) -> 1
J12: ● POSSÍVEL | K12: =COUNTIF('Relatório - Processos Ativos'!AA2:AA100,"POSSÍVEL") -> 0 | L12: {=IFERROR(SUMPRODUCT(NUMBERVALUE(SUBSTITUTE('Relatório - Processos Ativos'!Z2:Z100,"R$ ",""),",",".")*('Relatório - Processos Ativos'!AA2:AA100="POSSÍVEL")),0)} -> 0 | M12: =IF(K14=0,0,K12/K14) -> 0
J13: ● REMOTO | K13: =COUNTIF('Relatório - Processos Ativos'!AA2:AA100,"REMOTO") -> 0 | L13: {=IFERROR(SUMPRODUCT(NUMBERVALUE(SUBSTITUTE('Relatório - Processos Ativos'!Z2:Z100,"R$ ",""),",",".")*('Relatório - Processos Ativos'!AA2:AA100="REMOTO")),0)} -> 0 | M13: =IF(K14=0,0,K13/K14) -> 0
J14: TOTAL | K14: =SUM(K11:K13) -> 1 | L14: =SUM(L11:L13) -> 0 | M14: 1
B17: ▎ PROCEDIMENTOS ADMINISTRATIVOS
B18: PROCESSO | C18: DESCRIÇÃO | D18: STATUS | E18: RESULTADO
B19: Nenhum procedimento administrativo identificado no período
B21: ▎ PROCESSOS ARQUIVADOS / ENCERRADOS | J21: ▎ INDICADORES-CHAVE
B22: PROCESSO | C22: RECLAMANTE | D22: ENCERRAMENTO | E22: DESFECHO | F22: VALORES (R$) | J22: TOTAL DE PROCESSOS GERIDOS | K22: =B6+J6 -> 4 | L22: ativos + encerrados
B23: ='Processos arquivados'!B2 -> 1000188-41.2024.5.02.0264 | C23: ='Processos arquivados'!C2 -> DANDARA PEREIRA CAMARA | D23: ='Processos arquivados'!W2 -> 45484 | E23: ='Processos arquivados'!V2 -> ACORDO | F23: ='Processos arquivados'!S2 -> 500.04 | J23: VALOR TOTAL EM ACORDOS | K23: =SUM('Processos arquivados'!S2:S100) -> 3800.04 | L23: pagos em acordos
B24: ='Processos arquivados'!B3 -> 0010119-93.2023.5.15.0188 | C24: ='Processos arquivados'!C3 -> KELLY NUNES RODRIGUES CORDEIRO | D24: ='Processos arquivados'!W3 -> 45594 | E24: ='Processos arquivados'!V3 -> ACORDO | F24: ='Processos arquivados'!S3 -> 3300 | J24: TEMPO MÉDIO DE RESOLUÇÃO | K24: =TEXT(ROUND(AVERAGE(IFERROR('Processos arquivados'!W2-'Processos arquivados'!A2,0),IFERROR('Processos arquivados'!W3-'Processos arquivados'!A3,0),IFERROR('Processos arquivados'!W4-'Processos arquivados'!A4,844))/30,0),"0")&" meses" -> 17 meses | L24: média dos encerrados
B25: ='Processos arquivados'!B4 -> 1000524-79.2023.5.02.0361 | C25: ='Processos arquivados'!C4 -> BRUNA MATTOS | D25: ='Processos arquivados'!W4 -> 45901 | E25: IMPROCEDENTE | F25: ='Processos arquivados'!S4 -> 0 | J25: RISCO PREDOMINANTE | K25: PROVÁVEL | L25: maior concentração
B26: TOTAL PAGAMENTOS | E26: — | F26: =SUM(F23:F25) -> 3800.04 | J26: CONDENAÇÕES EFETIVAS | K26: =COUNTIF('Relatório - Processos Ativos'!AM2:AM100,"SIM") -> 1 | L26: com sentença desfavorável
B30: ▎ PRINCIPAIS PEDIDOS RECORRENTES | J30: ▎ STATUS / PRÓXIMOS PASSOS
B31: PEDIDO | C31: OCORRÊNCIAS | D31: FREQUÊNCIA | K31: PROCESSO | L31: STATUS / PRÓXIMA AÇÃO
B32: Horas Extras | C32: 4 | D32: =C32/4 -> 1 | J32: ⏳ | K32: 0010526-41... | L32: Fase Recursal — Recursos ordinários interpostos por ambas as partes
B33: Dano Moral | C33: 2 | D33: =C33/4 -> 0.5 | J33: ✅ | K33: 1000188-41... | L33: Acordo realizado — R$ 500,04
B34: Verbas Rescisórias / Reflexos | C34: 2 | D34: =C34/4 -> 0.5 | J34: ✅ | K34: 0010119-93... | L34: Acordo realizado — R$ 3.300,00
B35: Intervalo Intrajornada | C35: 1 | D35: =C35/4 -> 0.25 | J35: ✅ | K35: 1000524-79... | L35: Improcedente — RO negado provimento, RR negado
B36: Adicional Noturno | C36: 1 | D36: =C36/4 -> 0.25
B37: Reintegração / Estabilidade | C37: 1 | D37: =C37/4 -> 0.25
B40: ▎ DECISÕES JUDICIAIS POR INSTÂNCIA | J40: ▎ EVOLUÇÃO PROCESSUAL
B41: INSTÂNCIA | C41: FAVORÁVEL | D41: DESFAVORÁVEL | E41: TOTAL | J41: STATUS | K41: QTD | L41: % DO TOTAL | M41: DESFECHO
B42: 1º Grau | C42: 1 | D42: 1 | E42: =SUM(C42:D42) -> 2 | J42: Improcedência | K42: 1 | L42: =K42/K47 -> 0.25 | M42: FAVORÁVEL
B43: 2º Grau | C43: 1 | D43: 0 | E43: =SUM(C43:D43) -> 1 | J43: Acordo | K43: 2 | L43: =K43/K47 -> 0.5 | M43: FAVORÁVEL
B44: 3º Grau (TST) | C44: 1 | D44: 0 | E44: =SUM(C44:D44) -> 1 | J44: Em Andamento | K44: 1 | L44: =K44/K47 -> 0.25 | M44: PENDENTE
B45: TOTAL | C45: =SUM(C42:C44) -> 3 | D45: =SUM(D42:D44) -> 1 | E45: =SUM(E42:E44) -> 4 | J45: Condenação | K45: 0 | L45: =K45/K47 -> 0 | M45: DESFAVORÁVEL
J47: TOTAL | K47: =SUM(K42:K45) -> 4 | L47: 1 | M47: —
O49: Instância | P49: Favorável | Q49: Desfavorável | R49: Status | S49: QTD
O50: 1º Grau | P50: =C42 -> 1 | Q50: =D42 -> 1 | R50: Improcedência | S50: =K42 -> 1
O51: 2º Grau | P51: =C43 -> 1 | Q51: =D43 -> 0 | R51: Acordo | S51: =K43 -> 2
O52: 3º Grau (TST) | P52: =C44 -> 1 | Q52: =D44 -> 0 | R52: Em Andamento | S52: =K44 -> 1
R53: Condenação | S53: =K45 -> 0
B66: CUIDAR.ME • Relatório Contencioso Jurídico • Base: Março/2025 • Confidencial

Sheet Instruções - Lista de Unidades
A1: Grau de Risco | B1: Instruções - Preenchimento sobre o 'Valor do Processo' - Análise de Risco
A2: Possível | B2: Via de regra, análise quantitativa. Deverá ser considerado 50% do valor da causa. Na hipótese em que se considere uma análise qualitativa* (casos mais estratégicos), deverá ser indicado na coluna 'X'. No caso de improcedência, o processo deverá ser mantido como 'possível' até o trânsito em julgado da decisão. | D2: Observações: 1º)Mensalmente, o escritório deverá atualizar todas as informações da planilha e inserir, na coluna "C", a sigla da unidade com base no endereço, conforme a lista de unidades. 2º) Todas as alterações de provisionamento/alteração do valor deverão ser justificadas; 3º)No mês do arquivamento o processo deverá ser mantido como 'remoto' e serão preenchidas as colunas de 'BI' e 'BJ'. No relatório subsequente, o processo poderá ser movido para a aba de processos arquivados; * 4º) Entende-se por análise qualitativa aquela estimativa de valor baseada em conhecimento jurídico, jurisprudencial e doutrinário. 5º) Em alguns casos a CIA irá acionar o Seguro E&O (Seguro de Responsabilidade Civil), mas nesses casos nós avisaremos o escritório e o mesmo deverá preencher as colunas 'BA e 'BB'. 6º) Em casos de acordo o escritório deverá inserir o prognóstico "provável" e as informações na aba "acordos realizados"; 7º) O relatório deverá ser enviado mensalmente, impreterivelmente até o dia 20 de cada mês; 8º) Caso o campo da planilha não se aplique ao processo, o escritório deverá inserir “N/A” (não aplicável); 9º) Na coluna 'BA' (despesas processuais), o escritório deverá inserir todos os gastos que a companhia já teve para manter o processo;
A3: Provável | B3: Após decisão de parcial procedência/procedência. Deverá ser atualizado sempre que houver resultado de julgamento (recurso) ou iminência de pagamento (início de liquidação/cumprimento de sentença/homologação do valor em fase de liquidação/cumprimento). Na hipótese de acordo, deverá ser provisionado o valor acordado, com redução mensal do valor da parcela.
A4: Remoto | B4: Decisão improcedente transitada em julgado. Processo aguardando arquivamento.
A6: Unidades | B6: Endereço
B7: Av. das Nações Unidas, nº 12.995, Brooklin Paulista, CEP 04.578-911
A8: CORP | B8: Avenida Vital Brasil, 466 - Butantã
A9: BUTA | B9: R. Manoel da Nóbrega, nº 712 - Shopping Praça da Moça - Piso Palmeira - Centro
A10: DIAD | B10: Rua João Gonçalves, 261 - Centro
A11: GUAR | B11: Avenida Jandira, 40 - Indianópolis - SP
A12: IBIR | B12: Rua Engenheiro Camilo Olivetti - Vila Itapegica - Guarulhos
A13: INTE | B13: Av. José Pinheiro Borges, s/n, Shopping Metrô Itaquera, Lojas 547 a 550, Piso Campanela
A14: ITA2 | B14: Av. José Pinheiro Borges, s/n - Shopping Metrô Itaquera, Lojas 149/150/151/152, Piso Metrô
A15: ITAQ | B15: Rua dos Buritis, 128, Loja 1-B e 2-B, Térreo, Bloco B - Bairro Vila Parque Jabaquara
A16: JABA | B16: Rua John Harrison, 47
A17: LAPA | B17: Rua Brigadeiro Tobias, 600 - Loja Térreo
A18: MLUZ | B18: Av. Paes de Barros, 75 - Mooca
A19: MOOC | B19: Rua Dona Primitiva Vianco, 145 - Loja 01 Térreo
... A35: TREZ | B35: Av Tucuruvi, 990 - Tucuruvi
A36: COOP

Sheet Relatório - Processos Ativos
A1: Escritório | B1: Empresa do Grupo | C1: Unidade (sigla) | D1: Parte(s) Contrária(s) | E1: Outros Integrantes - Polo Passivo | F1: Número do Processo | G1: Objeto da lide | H1: Médico Envolvido | I1: Especialidade Médica envolvida | J1: Tipo de Reclamação | K1: Complemento | L1: Tipo de Exame Envolvido | M1: Há pedido de Dano Moral? | N1: Há pedido de Dano Material? | O1: Há pedido de Dano Estético? | P1: Ano do Fato Gerador | Q1: Data do Ajuizamento (dia/mês/ano) | R1: Data de cadastro na base do Escritório | S1: Natureza | T1: Estado | U1: Comarca | V1: Vara/Foro | W1: Jurisdição | X1: Escritório da Parte Contrária | Y1: Resumo da Petição Inicial com Pedidos | Z1: Valor da Causa | AA1: Risco Setembro/2025 | AB1: Valor Abril/2025 | AC1: Análise Qualitativa? | AD1: Houve alteração do valor de provisionamento | AE1: Valor de alteração | AF1: Justificativa para alteração do valor de provisionamento | AG1: Fase Atual do Processo | AH1: Liminar? | AI1: Perícia solicitada | AJ1: Tipo de Perícia solicitada | AK1: Data Resultado da Perícia | AL1: Resultado da Perícia | AM1: Houve Sentença | AN1: Data Sentença | AO1: Resultado da Sentença | AP1: Dispositivo da Sentença | AQ1: Valor da Condenação | AR1: Houve Recurso de Apelação/Recurso Inominado | AS1: Data do Acórdão | AT1: Resultado do Acórdão | AU1: Condenação em Sede Recursal (Valor) | AV1: Recurso Especial/Recurso Extraordinário | AW1: Data Acórdão2 | AX1: Resultado do Acórdão2 | AY1: Total de Despesas Processuais | AZ1: A CIA acionou o Seguro E&O? | BA1: Houve Acordo | BB1: Data do acordo | BC1: Valor do Acordo | BD1: Economia CIA | BE1: Data do Trânsito em Julgado | BF1: Ultimo andamento | BG1: Depósito Judicial | BH1: Observações | BI1: Motivo do Encerramento | BJ1: Data do Encerramento
A2: FALAW | B2: CUIDAR.ME | D2: ADRIANO SOARES DE LIMA | F2: 0010526-41.2024.5.15.0002 | G2: Trata-se de reclamação trabalhista ajuizada pelo reclamante em face da empresa. O reclamante foi contratado em 23/08/2022 para exercer a função de supervisor técnico regulatório, com salário mensal de R$ 5.000,00, sendo dispensado sem justa causa em 03/12/2023. Na ação, o reclamante formula pedidos de: Pagamento de horas extras e reflexos em RSR, feriados, férias + 1/3, 13º salário, aviso prévio e FGTS + 40%; Pagamento em dobro de feriados trabalhados e não compensados; Reconhecimento de que os valores atribuídos aos pedidos são meramente estimativos, não limitando a liquidação futura; Condenação ao pagamento de honorários advocatícios de sucumbência (art. 791-A da CLT), entre 5% e 15% sobre o valor da condenação; Concessão do benefício da justiça gratuita, com fundamento na hipossuficiência econômica e no art. 5º, LXXIV, da Constituição Federal. | H2: N/A | I2: N/A | J2: TRABALHISTA | K2: N/A | L2: N/A | M2: Não | N2: Não | O2: N/A | P2: 2024 | Q2: 45369 | S2: TRABALHISTA | T2: SP | U2: JUNDIAÍ | V2: 1ª | W2: JUSTIÇA DO TRABALHO | X2: FURTADO ADVOGADOS ASSOCIADOS | Y2: Em síntese, a ação busca o reconhecimento da jornada extraordinária não paga, o recebimento das verbas rescisórias e reflexos, além da concessão da justiça gratuita e honorários advocatícios, com a condenação da reclamada ao pagamento dos direitos trabalhistas não adimplidos. | Z2: R$ 110.248,73 | AA2: PROVÁVEL | AB2: R$ 110.248,73 | AC2: N/A | AD2: NÃO | AE2: N/A | AF2: N/A | AG2: RECURSAL | AH2: NÃO | AI2: NÃO | AJ2: N/A | AK2: N/A | AL2: N/A | AM2: SIM | AN2: 45916 | AO2: Foi proferida sentença que julgou os pedidos procedentes. | AP2: PROCEDENTES os pedidos formulados por ADRIANO SOARES DE LIMA em face de CUIDAR.ME SAUDE LTDA para condenar a reclamada a pagar a(o) autor(a), conforme for apurado e nos termos da fundamentação, todos os títulos deferidos nesta sentença. | AQ2: 120000 | AR2: Foram interpostos recursos ordinários por ambas as partes | AS2: N/A | AT2: N/A | AU2: N/A | AV2: N/A | AW2: N/A | AX2: N/A | AY2: N/A | AZ2: N/A | BA2: N/A | BB2: N/A | BC2: N/A | BD2: N/A | BE2: N/A | BF2: 46099 | BG2: 13813.83 | BH2: N/A | BI2: N/A | BJ2: N/A

Sheet Processos arquivados
A1: Data do Ajuizamento | B1: Número do Processo | C1: Parte(s) Contrária(s) | D1: Empresa do Grupo | E1: Unidade (sigla) | F1: Outros Integrantes - Polo Passivo | G1: Médico Envolvido | H1: Especialidade Médica envolvida | I1: Fato Gerador | J1: Ano do Fato Gerador | K1: Natureza | L1: Estado | M1: Comarca | N1: Vara/Foro | O1: Jurisdição | P1: Escritório da Parte Contrária | Q1: Resumo da Petição Inicial com Pedidos | R1: Houve Acordo | S1: Valor do Acordo | T1: Último movimentação processual | U1: Observações | V1: Motivo do Encerramento | W1: Data do Encerramento
A2: 45345 | B2: 1000188-41.2024.5.02.0264 | C2: DANDARA PEREIRA CAMARA | D2: CUIDAR.ME | F2: N/A | G2: N/A | H2: N/A | I2: N/A | J2: N/A | K2: TRABALHISTA | L2: SP | M2: DIADEMA | N2: 4ª Vara do Trabalho de Diadema | O2: JUSTIÇA DO TRABALHO | P2: Christian Regis da Cruz | Q2: A reclamante alega ter feito jornadas excessivas, bem como intervalo reduzido. Sofreu constantes humilhações e tratamento grosseiro por parte da gestora. PEDIDOS: Horas extras; Intervalo intrajornada; Dano moral | R2: SIM | S2: 500.04 | T2: 45484 | U2: N/A | V2: ACORDO | W2: 45484
A3: 45014 | B3: 0010119-93.2023.5.15.0188 | C3: KELLY NUNES RODRIGUES CORDEIRO | D3: CUIDAR.ME | F3: N/A | G3: N/A | H3: N/A | I3: N/A | J3: N/A | K3: TRABALHISTA | L3: SP | M3: JUNDIAÍ | N3: 5ª Vara do Trabalho de Jundiaí | O3: JUSTIÇA DO TRABALHO | P3: Santos e Santana | Q3: Alega a reclamante que exerce mais de uma atividade, trabalhava a noite sem receber adicional noturno. PEDIDOS: Adicional Noturno; Hora Extra; Dispensa Discriminatória; Teletrabalho | R3: SIM | S3: 3300 | T3: 45594 | U3: N/A | V3: ACORDO | W3: 45594
A4: 10/05/2023 | B4: 1000524-79.2023.5.02.0361 | C4: BRUNA MATTOS | D4: CUIDAR.ME | F4: N/A | G4: N/A | H4: N/A | I4: N/A | J4: N/A | K4: TRABALHISTA | L4: SP | M4: MAUÁ | N4: 1ª Vara do Trabalho de Mauá | O4: JUSTIÇA DO TRABALHO | P4: MK Advocacia e Consultoria Jurídica | Q4: A Reclamante alega ter sido vítima de doença ocupacional, sustentando que a dispensa ocorrida teria caráter discriminatório, motivo pelo qual requer a reintegração. Postula, ainda, indenização por danos morais e reconhecimento de estabilidade | R4: NÃO | S4: 0 | T4: 45901 | U4: Ação improcedente, RO negado provimento, bem como RR. | V4: N/A | W4: 45901

Sheet Acordos realizados
A1: Empresa do Grupo | B1: Unidade (sigla) | C1: Parte(s) Contrária(s) | D1: Outros Integrantes - Polo Passivo | E1: Número do Processo | F1: Médico Envolvido | G1: Especialidade Médica envolvida | H1: Tipo de Reclamação | I1: Complemento | J1: Data de cadastro na base do Escritório | K1: Estado | L1: Comarca | M1: Vara/Foro | N1: Jurisdição | O1: Escritório da Parte Contrária | P1: Resumo da Petição Inicial com Pedidos | Q1: Valor da Causa | R1: Valor Acordo | S1: Data do acordo | T1: Data do Protocolo | U1: Multa | V1: Último valor contingenciado | W1: Economia CIA
B2: CORP
