Workbook

Sheet DASHBOARD
B2: RELATÓRIO MENSAL | ABRIL/2026
B5: PROCESSOS ATIVOS | E5: EXPOSIÇÃO TOTAL | J5: PROCESSOS ENCERRADOS | N5: TAXA DE ÊXITO
B6: =COUNTA(ATIVOS!C3:C36) -> 34 | E6: =SUM(ATIVOS!AM3:AM36) -> 4908003.4 | J6: =COUNTA(ENCERRADOS!B3:B67) -> 65 | N6: =(COUNTIF(ENCERRADOS!E3:E67,"IMPROCEDÊNCIA")+COUNTIF(ENCERRADOS!E3:E67,"ACORDO ENTRE AS PARTES")+COUNTIF(ENCERRADOS!E3:E67,"EXTINTO SEM RESOLUÇÃO DO MÉRITO")+COUNTIF(ENCERRADOS!E3:E67,"EXCLUSÃO DA FRETE")+COUNTIF(ENCERRADOS!E3:E67,"DESISTÊNCIA DA AÇÃO")+COUNTIF(ENCERRADOS!E3:E67,"DESISTÊNCIA DA AÇÃO EM FASE DA FRETE")+COUNTIF(ENCERRADOS!E3:E67,"AUSÊNCIA DO RECLAMANTE NA AUDIÊNCIA"))/COUNTA(ENCERRADOS!E3:E67) -> 0.44615385
B7: em andamento | E7: valor da causa | J7: no período | N7: casos favoráveis
B9: ▎ PROCESSOS ATIVOS — RISCO PROVÁVEL | J9: ▎ DISTRIBUIÇÃO POR RISCO
B10: PROCESSO | C10: RECLAMANTE | D10: VALOR (R$) | E10: RISCO | F10: FASE ATUAL | J10: CLASSIFICAÇÃO | K10: QTD | L10: VALOR (R$) | M10: % DO TOTAL
B11: =ATIVOS!C3 -> 1001370-57.2020.5.02.0020 | C11: =ATIVOS!D3 -> LUCENIR SANTOS MOREIRA | D11: =ATIVOS!AM3 -> 227780 | E11: =ATIVOS!M3 -> PROVÁVEL | F11: =ATIVOS!K3 -> RECURSAL | J11: ● PROVÁVEL | K11: =COUNTIF(ATIVOS!M3:M36,"PROVÁVEL") -> 16 | L11: =SUMIF(ATIVOS!M3:M36,"PROVÁVEL",ATIVOS!AM3:AM36) -> 1906370.3 | M11: =K11/K14 -> 0.47058824
B12: =ATIVOS!C4 -> 1001244-93.2022.5.02.0001 | C12: =ATIVOS!D4 -> LEANDRO DE OLIVEIRA SANTOS | D12: =ATIVOS!AM4 -> 103589 | E12: =ATIVOS!M4 -> PROVÁVEL | F12: =ATIVOS!K4 -> RECURSAL | J12: ● POSSÍVEL | K12: =COUNTIF(ATIVOS!M3:M36,"POSSÍVEL") -> 9 | L12: =SUMIF(ATIVOS!M3:M36,"POSSÍVEL",ATIVOS!AM3:AM36) -> 1787133.7 | M12: =K12/K14 -> 0.26470588
B13: =ATIVOS!C6 -> 1000392-52.2023.5.02.0060 | C13: =ATIVOS!D6 -> MAYCON DE ARAUJO BIZERRA | D13: =ATIVOS!AM6 -> 26024.24 | E13: =ATIVOS!M6 -> PROVÁVEL | F13: =ATIVOS!K6 -> RECURSAL | J13: ● REMOTO | K13: =COUNTIF(ATIVOS!M3:M36,"REMOTO") -> 9 | L13: =SUMIF(ATIVOS!M3:M36,"REMOTO",ATIVOS!AM3:AM36) -> 1214499.4 | M13: =K13/K14 -> 0.26470588
B14: =ATIVOS!C8 -> 1000637-34.2023.5.02.0005 | C14: =ATIVOS!D8 -> GISELE BRITO COSTA | D14: =ATIVOS!AM8 -> 153000 | E14: =ATIVOS!M8 -> PROVÁVEL | F14: =ATIVOS!K8 -> RECURSAL | J14: TOTAL | K14: =SUM(K11:K13) -> 34 | L14: =SUM(L11:L13) -> 4908003.4 | M14: =SUM(M11:M13) -> 1
B15: =ATIVOS!C12 -> 1001955-81.2023.5.02.0060 | C15: =ATIVOS!D12 -> CAMILA REBEQUI | D15: =ATIVOS!AM12 -> 204622 | E15: =ATIVOS!M12 -> PROVÁVEL | F15: =ATIVOS!K12 -> EXECUÇÃO
B16: =ATIVOS!C14 -> 0016045-64.2024.5.16.0003 | C16: =ATIVOS!D14 -> QLIVHYA HADHAYA VIEIRA MOREIRA | D16: =ATIVOS!AM14 -> 149452.33 | E16: =ATIVOS!M14 -> PROVÁVEL | F16: =ATIVOS!K14 -> EXECUÇÃO
B17: =ATIVOS!C16 -> 1000938-82.2024.5.02.0057 | C17: =ATIVOS!D16 -> MARIA APARECIDA SOLLA | D17: =ATIVOS!AM16 -> 126957.39 | E17: =ATIVOS!M16 -> PROVÁVEL | F17: =ATIVOS!K16 -> EXECUÇÃO | J17: ▎ PROCEDIMENTOS ADMINISTRATIVOS
B18: =ATIVOS!C17 -> 1002094-96.2024.5.02.0060 | C18: =ATIVOS!D17 -> CAMILA REBEQUI | D18: =ATIVOS!AM17 -> 64589.79 | E18: =ATIVOS!M17 -> PROVÁVEL | F18: =ATIVOS!K17 -> RECURSAL | J18: PROCESSO | K18: DESCRIÇÃO | L18: STATUS | M18: RESULTADO
B19: =ATIVOS!C19 -> 1000419-12.2025.5.02.0045 | C19: =ATIVOS!D19 -> JESSICA GOUVEIA LUIZ | D19: =ATIVOS!AM19 -> 48240.89 | E19: =ATIVOS!M19 -> PROVÁVEL | F19: =ATIVOS!K19 -> EXECUÇÃO | J19: ='PROCEDIMENTO ADMINISTRATIVO'!B3 -> 14152.037968/2022-86 | K19: ='PROCEDIMENTO ADMINISTRATIVO'!H3 -> Autuado por deixar de apresentar documentos sujeitos à inspeção do trabalho no dia e hora previamente fixados pelo AFT. | L19: ='PROCEDIMENTO ADMINISTRATIVO'!I3 -> Arquivado | M19: Arquivado
B20: =ATIVOS!C20 -> 1000414-10.2025.5.02.0006 | C20: =ATIVOS!D20 -> FERNANDO ROGERIO BARBOSA DE BARROS | D20: =ATIVOS!AM20 -> 108794.5 | E20: =ATIVOS!M20 -> PROVÁVEL | F20: =ATIVOS!K20 -> EXECUÇÃO | J20: ='PROCEDIMENTO ADMINISTRATIVO'!B4 -> 14152.037962/2022-17 | K20: ='PROCEDIMENTO ADMINISTRATIVO'!H4 -> Autuado por deixar de empregar aprendizes em número equivalente a 5% (cinco por cento), no mínimo, dos empregados existentes em cada estabelecimento, cujas funções demandem formação profissional. | L20: ='PROCEDIMENTO ADMINISTRATIVO'!I4 -> Arquivado | M20: Arquivado
B21: =ATIVOS!C28 -> 1001427-86.2025.5.02.0089 | C21: =ATIVOS!D28 -> DIOGO BARBOSA SOARES | D21: =ATIVOS!AM28 -> 169485.28 | E21: =ATIVOS!M28 -> PROVÁVEL | F21: =ATIVOS!K28 -> EXECUÇÃO | J21: ='PROCEDIMENTO ADMINISTRATIVO'!B5 -> 3658/2022 | K21: ='PROCEDIMENTO ADMINISTRATIVO'!H5 -> Não preenchimento de cota (PCD) | L21: ='PROCEDIMENTO ADMINISTRATIVO'!I5 -> APRESENTAMOS DEFESA - ASSINAMOS TERMO DE COMPROMISSO DE ADEQUAÇÃO DA COTA (PCD). | M21: Termo de Compromisso
B22: =ATIVOS!C5 -> 1000255-97.2023.5.02.0051 | C22: =ATIVOS!D5 -> GUSTAVO PAROLINI | D22: =ATIVOS!AM5 -> 94622.09 | E22: =ATIVOS!M5 -> PROVÁVEL | F22: =ATIVOS!K5 -> RECURSAL
B23: =ATIVOS!C9 -> 1001217-34.2023.5.02.0015 | C23: =ATIVOS!D9 -> CICERO RAMON SANTOS ALVES | D23: =ATIVOS!AM9 -> 188835 | E23: =ATIVOS!M9 -> PROVÁVEL | F23: =ATIVOS!K9 -> RECURSAL
B24: =ATIVOS!C23 -> 1001267-10.2025.5.02.0203 | C24: =ATIVOS!D23 -> DIMITRI FERREIRA DE PAULA E SILVA | D24: =ATIVOS!AM23 -> 149091.42 | E24: =ATIVOS!M23 -> PROVÁVEL | F24: =ATIVOS!K23 -> RECURSAL
B25: =ATIVOS!C24 -> 1001038-32.2025.5.02.0015 | C25: =ATIVOS!D24 -> CICERO RAMON SANTOS ALVES | D25: =ATIVOS!AM24 -> 52552.02 | E25: =ATIVOS!M24 -> PROVÁVEL | F25: =ATIVOS!K24 -> CONHECIMENTO
B26: =ATIVOS!C36 -> 1000294-87.2026.5.02.0084 | C26: =ATIVOS!D36 -> SOPHYA SECCHIERO LISBOA | D26: =ATIVOS!AM36 -> 38734.36 | E26: =ATIVOS!M36 -> PROVÁVEL | F26: =ATIVOS!K36 -> EXECUÇÃO
J29: ▎ PROCESSOS ENCERRADOS — IMPROCEDÊNCIA TOTAL
J30: PROCESSO | K30: RECLAMANTE | L30: ENCERRAMENTO | M30: DESFECHO | N30: VALORES (R$)
J31: =ENCERRADOS!B36 -> 1001088-37.2022.5.02.0056 | K31: =ENCERRADOS!C36 -> EDER ENRIQUE ARRIAGADA BIANCIOTTO | L31: =ENCERRADOS!D36 -> 45467 | M31: =ENCERRADOS!E36 -> IMPROCEDÊNCIA | N31: =ENCERRADOS!F36 -> 0
J32: =ENCERRADOS!B41 -> 1001273-74.2022.5.02.0024 | K32: =ENCERRADOS!C41 -> WILLIAN KACZMARECK FITIPALDI | L32: =ENCERRADOS!D41 -> 45616 | M32: =ENCERRADOS!E41 -> IMPROCEDÊNCIA | N32: =ENCERRADOS!F41 -> 0
J33: =ENCERRADOS!B44 -> 1001316-31.2023.5.02.0006 | K33: =ENCERRADOS!C44 -> IVAN DE SOUSA AMORIM | L33: =ENCERRADOS!D44 -> 45664 | M33: =ENCERRADOS!E44 -> IMPROCEDÊNCIA | N33: =ENCERRADOS!F44 -> 0
J34: =ENCERRADOS!B53 -> 1000271-48.2024.5.02.0073 | K34: =ENCERRADOS!C53 -> MATHEUS ANDRADE DE OLIVEIRA | L34: =ENCERRADOS!D53 -> 45793 | M34: =ENCERRADOS!E53 -> IMPROCEDÊNCIA | N34: =ENCERRADOS!F53 -> 0
J35: =ENCERRADOS!B54 -> 1000964-52.2022.5.02.0089 | K35: =ENCERRADOS!C54 -> FRANCISCO CESAR PIRES DOS SANTOS | L35: =ENCERRADOS!D54 -> 45831 | M35: =ENCERRADOS!E54 -> IMPROCEDÊNCIA | N35: =ENCERRADOS!F54 -> 0
J36: =ENCERRADOS!B61 -> 0000617-81.2023.5.09.0129 | K36: =ENCERRADOS!C61 -> SIDNEI EIJI NISHIYAMA | L36: =ENCERRADOS!D61 -> 45967 | M36: =ENCERRADOS!E61 -> IMPROCEDÊNCIA | N36: =ENCERRADOS!F61 -> 0
J37: TOTAL IMPROCEDÊNCIAS | K37: =COUNTA(J31:J36) -> 6 | N37: =SUM(N31:N36) -> 0
B49: ▎ INDICADORES-CHAVE
B50: TOTAL DE PROCESSOS GERIDOS
B51: =B6+J6 -> 99 | C51: ativos + encerrados
B53: VALOR TOTAL EM ACORDOS
B54: =SUMIF(ENCERRADOS!E3:E67,"ACORDO ENTRE AS PARTES",ENCERRADOS!F3:F67)+SUM(ATIVOS!AQ3:AQ36) -> 612443 | C54: soma dos acordos
B56: TEMPO MÉDIO DE RESOLUÇÃO
B57: ~24 meses | C57: estimativa média
B59: RISCO PREDOMINANTE
B60: =IF(K11>=K12,IF(K11>=K13,"PROVÁVEL","REMOTO"),IF(K12>=K13,"POSSÍVEL","REMOTO")) -> PROVÁVEL | C60: maior concentração
B62: CONDENAÇÕES EFETIVAS
B63: =COUNTIF(ATIVOS!Y3:Y36,"DESFAVORÁVEL") -> 18 | C63: processos com condenação
B65: ▎ PRINCIPAIS PEDIDOS RECORRENTES | E65: ▎ STATUS / PRÓXIMOS PASSOS
B66: PEDIDO | C66: OCORRÊNCIAS | D66: FREQUÊNCIA | F66: STATUS / PRÓXIMA AÇÃO
B67: Horas Extras | C67: =COUNTIF(ATIVOS!Q3:Q36,"*Horas extras*") -> 16 | D67: =C67/COUNTA(ATIVOS!C3:C36) -> 0.47058824 | E67: ⏳ | F67: =ATIVOS!L3 -> AGUARDANDO JULGAMENTO DO AGRAVO DE INSTRUMENTO
B68: Equiparação Salarial | C68: =COUNTIF(ATIVOS!Q3:Q36,"*Equiparação*") -> 7 | D68: =C68/COUNTA(ATIVOS!C3:C36) -> 0.20588235 | E68: ⏳ | F68: =ATIVOS!L4 -> AGUARDANDO JULGAMENTO DO AGRAVO DE INSTRUMENTO
B69: Intervalo Intrajornada | C69: =COUNTIF(ATIVOS!Q3:Q36,"*Intervalo intrajornada*") -> 10 | D69: =C69/COUNTA(ATIVOS!C3:C36) -> 0.29411765 | E69: ⏳ | F69: =ATIVOS!L5 -> AGUARDANDO JULGAMENTO DO AGRAVO INTERNO
B70: Honorários de Sucumbência | C70: =COUNTIF(ATIVOS!Q3:Q36,"*Honorários*") -> 28 | D70: =C70/COUNTA(ATIVOS!C3:C36) -> 0.82352941 | E70: ⏳ | F70: =ATIVOS!L6 -> AGUARDANDO JULGAMENTO DO AGRAVO INTERNO
B71: Dano Moral | C71: =COUNTIF(ATIVOS!Q3:Q36,"*dano moral*") -> 15 | D71: =C71/COUNTA(ATIVOS!C3:C36) -> 0.44117647 | E71: ⏳ | F71: =ATIVOS!L7 -> AGUARDANDO JULGAMENTO DO AGRAVO INTERNO
B72: Verbas Rescisórias | C72: =COUNTIF(ATIVOS!Q3:Q36,"*Verbas rescisórias*") -> 9 | D72: =C72/COUNTA(ATIVOS!C3:C36) -> 0.26470588 | E72: ⏳ | F72: =ATIVOS!L8 -> AGUARDANDO JULGAMENTO DO AGRAVO DE PETIÇÃO
B73: DSR / Comissões | C73: =COUNTIF(ATIVOS!Q3:Q36,"*DSR*")+COUNTIF(ATIVOS!Q3:Q36,"*Comiss*") -> 13 | D73: =C73/COUNTA(ATIVOS!C3:C36) -> 0.38235294 | E73: ⏳ | F73: =ATIVOS!L9 -> AGUARDANDO JULGAMENTO DO AGRAVO DE INSTRUMENTO
B74: FGTS / Multa 40% | C74: =COUNTIF(ATIVOS!Q3:Q36,"*FGTS*") -> 10 | D74: =C74/COUNTA(ATIVOS!C3:C36) -> 0.29411765 | E74: ⏳ | F74: =ATIVOS!L10 -> INÍCIO DA EXECUÇÃO
B76: ▎ DECISÕES JUDICIAIS POR INSTÂNCIA
B77: INSTÂNCIA | C77: FAVORÁVEL | D77: DESFAVORÁVEL | E77: TOTAL
B78: 1º Grau | C78: =COUNTIF(ATIVOS!Y3:Y36,"FAVORÁVEL") -> 4 | D78: =COUNTIF(ATIVOS!Y3:Y36,"DESFAVORÁVEL") -> 18 | E78: =C78+D78 -> 22
B79: 2º Grau | C79: =COUNTIF(ATIVOS!AC3:AC36,"FAVORÁVEL") -> 7 | D79: =COUNTIF(ATIVOS!AC3:AC36,"DESFAVORÁVEL") -> 11 | E79: =C79+D79 -> 18
B80: TOTAL | C80: =SUM(C78:C79) -> 11 | D80: =SUM(D78:D79) -> 29 | E80: =SUM(E78:E79) -> 40
J99: ▎ EVOLUÇÃO PROCESSUAL
J100: STATUS | K100: QTD | L100: % DO TOTAL | M100: DESFECHO | N100: VALOR PAGO (R$)
J101: Improcedência | K101: =COUNTIF(ENCERRADOS!E3:E67,"IMPROCEDÊNCIA") -> 6 | L101: =K101/K106 -> 0.064516129 | M101: Favorável | N101: =SUMIF(ENCERRADOS!E3:E67,"IMPROCEDÊNCIA",ENCERRADOS!F3:F67) -> 0
J102: Extinção c/ Mérito | K102: =COUNTIF(ENCERRADOS!E3:E67,"EXTINTO SEM RESOLUÇÃO DO MÉRITO")+COUNTIF(ENCERRADOS!E3:E67,"DESISTÊNCIA DA AÇÃO")+COUNTIF(ENCERRADOS!E3:E67,"DESISTÊNCIA DA AÇÃO EM FASE DA FRETE")+COUNTIF(ENCERRADOS!E3:E67,"EXCLUSÃO DA FRETE")+COUNTIF(ENCERRADOS!E3:E67,"AUSÊNCIA DO RECLAMANTE NA AUDIÊNCIA") -> 6 | L102: =K102/K106 -> 0.064516129 | M102: Favorável | N102: 0
J103: Acordo | K103: =COUNTIF(ENCERRADOS!E3:E67,"ACORDO ENTRE AS PARTES") -> 17 | L103: =K103/K106 -> 0.1827957 | M103: Acordo | N103: =SUMIF(ENCERRADOS!E3:E67,"ACORDO ENTRE AS PARTES",ENCERRADOS!F3:F67) -> 587443
J104: Em Andamento | K104: =B6 -> 34 | L104: =K104/K106 -> 0.3655914 | M104: Pendente | N104: —
J105: Condenação | K105: =COUNTIF(ENCERRADOS!E3:E67,"EXECUÇÃO FINALIZADA") -> 30 | L105: =K105/K106 -> 0.32258065 | M105: Desfavorável | N105: =SUMIF(ENCERRADOS!E3:E67,"EXECUÇÃO FINALIZADA",ENCERRADOS!F3:F67) -> 378351.11
J106: TOTAL | K106: =SUM(K101:K105) -> 93 | L106: =SUM(L101:L105) -> 1 | N106: =SUM(N101:N105) -> 965794.11
B110: ▎ RANKING — JUÍZES FAVORÁVEIS | J110: ▎ RANKING — JUÍZES DESFAVORÁVEIS
B111: JULGADOR | C111: INSTÂNCIA | D111: FAVORÁVEIS | E111: TOTAL | F111: % ÊXITO | J111: JULGADOR | K111: INSTÂNCIA | L111: DESFAV. | M111: TOTAL | N111: % DESFAV.
B112: Amaury Rodrigues Pinto Junior | C112: TST | D112: 3 | E112: 3 | F112: 1 | J112: Leticia Neto Amaral | K112: 1º Grau | L112: 2 | M112: 2 | N112: 1
B113: Marina de Almeida Aoki | C113: 1º Grau | D113: 1 | E113: 1 | F113: 1 | J113: Rita de Cassia Martinez | K113: 1º Grau | L113: 1 | M113: 1 | N113: 1
B114: Luciana Siqueira Alves Garcia | C114: 1º Grau | D114: 1 | E114: 1 | F114: 1 | J114: Jeronimo Azambuja Franco Neto | K114: 1º Grau | L114: 1 | M114: 1 | N114: 1
B115: Fernando Maidana Miguel | C115: 1º Grau | D115: 1 | E115: 1 | F115: 1 | J115: Cláudia Tejeda Costa | K115: 1º Grau | L115: 1 | M115: 1 | N115: 1
B116: Vinícius Daniel Petry | C116: 1º Grau | D116: 1 | E116: 1 | F116: 1 | J116: Eudivan Batista de Souza | K116: 1º Grau | L116: 1 | M116: 1 | N116: 1
B117: Jorge Eduardo Assad | C117: 2º Grau | D117: 1 | E117: 1 | F117: 1 | J117: Talita Luci Mendes Falcão | K117: 1º Grau | L117: 1 | M117: 1 | N117: 1
B118: Maria de Lourdes Antonio | C118: 2º Grau | D118: 1 | E118: 1 | F118: 1 | J118: Marcelo Pereira das Neves | K118: 1º Grau | L118: 1 | M118: 1 | N118: 1
B119: Sônia Maria de Barros | C119: 2º Grau | D119: 1 | E119: 1 | F119: 1 | J119: Ana Maria M. Barbosa Macedo | K119: 2º Grau | L119: 1 | M119: 1 | N119: 1
B120: James Magno Araújo Farias | C120: 2º Grau | D120: 1 | E120: 1 | F120: 1 | J120: Sônia Maria Forster do Amaral | K120: 2º Grau | L120: 1 | M120: 1 | N120: 1
B121: Luís Carlos G. Carneiro Filho | C121: 2º Grau | D121: 1 | E121: 1 | F121: 1 | J121: Ricardo A. Costa e Trigueiros | K121: 2º Grau | L121: 1 | M121: 1 | N121: 1
B122: Daniel de Paula Guimarães | C122: 2º Grau | D122: 1 | E122: 1 | F122: 1 | J122: Magda Cardoso Mateus Silva | K122: 2º Grau | L122: 1 | M122: 1 | N122: 1
B123: Angela Rosi Almeida Chapper | C123: 2º Grau | D123: 1 | E123: 1 | F123: 1 | J123: Alexandre Luiz Ramos | K123: TST | L123: 1 | M123: 1 | N123: 1
B126: ▎ RANKING — ADVOGADOS CONTRÁRIOS (PROCESSOS ATIVOS) | J126: ▎ CONCENTRAÇÃO DE RISCO — ADVOGADOS
B127: ESCRITÓRIO / ADVOGADO | C127: QTD PROCESSOS | D127: % DO TOTAL | E127: DESTAQUE | J127: TOP 3 ESCRITÓRIOS | L127: PROCESSOS | M127: % TOTAL | N127: RISCO
B128: Rodrigues & Miranda Advogados Associados | C128: 9 | D128: =C128/C137 -> 0.26470588 | E128: ⚠ RECORRENTE | J128: Rodrigues & Miranda | L128: 9 | M128: =L128/C137 -> 0.26470588 | N128: ⚠ ALTO
B129: Martins & Fernandes Advogados Associados | C129: 3 | D129: =C129/C137 -> 0.088235294 | J129: Martins & Fernandes | L129: 3 | M129: =L129/C137 -> 0.088235294 | N129: ● MÉDIO
B130: Lima Advogados Associados | C130: 2 | D130: =C130/C137 -> 0.058823529 | J130: Lima / Zamith / Calliari | L130: 6 | M130: =L130/C137 -> 0.17647059 | N130: ● BAIXO
B131: Zamith Assessoria Jurídica | C131: 2 | D131: =C131/C137 -> 0.058823529
B132: Calliari & Teixeira Advogados Associados | C132: 2 | D132: =C132/C137 -> 0.058823529 | J132: INSIGHT
B133: A.S. Azevedo Sociedade de Advogados | C133: 1 | D133: =C133/C137 -> 0.029411765 | J133: O escritório Rodrigues & Miranda concentra
B134: Angela Perez Advogados | C134: 1 | D134: =C134/C137 -> 0.029411765 | J134: 26% dos processos ativos, representando o
B135: Melges & Menegueti Advogados Associados | C135: 1 | D135: =C135/C137 -> 0.029411765 | J135: maior risco de concentração adversarial.
B136: Demais escritórios (1 processo cada) | C136: 13 | D136: =C136/C137 -> 0.38235294 | J136: Os Top 3 somam 53% de toda a carteira.
B137: TOTAL | C137: =SUM(C128:C136) -> 34 | D137: =SUM(D128:D136) -> 1
B153: FRETEBRAS / CARGOX • Relatório Contencioso Jurídico • Base: Abril/2026 • Confidencial

Sheet ATIVOS
A1: PROCESSOS ATIVOS - ABRIL/2026
A2: DATA DA DISTRIBUIÇÃO | B2: TRT | C2: NÚMERO DO PROCESSO | D2: PARTE CONTRÁRIA | E2: ADV. CONTRÁRIO | F2: PARTE PRINCIPAL | G2: EMPRESA TERCEIRA | H2: TIPO DE AÇÃO | I2: RESPONSABILIDADE | J2: FUNÇÃO/CARGO | K2: FASE | L2: STATUS ATUAL | M2: RISCO | N2: ÓRGÃO | O2: INSTÂNCIA | P2: CIDADE/UF | Q2: PEDIDOS E VALOR | R2: RESUMO DA AUDIÊNCIA | S2: DATA DA AUDIÊNCIA DE INSTRUÇÃO | T2: PREPOSTO | U2: TESTEMUNHA DA RECLAMADA | V2: TESTEMUNHA DO RECLAMANTE | W2: LAUDO PERICIAL | X2: PERITO | Y2: SENTENÇA | Z2: JULGADOR DE 1º GRAU | AA2: DATA DA SENTENÇA | AB2: RESUMO DA SENTENÇA | AC2: ACÓRDÃO | AD2: JULGADOR DE 2º GRAU | AE2: TURMA | AF2: DATA DO ACÓRDÃO | AG2: RESUMO DO ACÓRDÃO | AH2: DECISÃO DO TST | AI2: JULGADOR DO 3º GRAU | AJ2: TURMA | AK2: DATA DA DECISÃO | AL2: RESUMO DA DECISÃO | AM2: VALOR DA CAUSA | AN2: VALOR DA CONDENAÇÃO | AO2: CÁLCULOS DO RECLAMANTE | AP2: CÁLCULOS DA RECLAMADA | AQ2: VALOR DO ACORDO | AR2: DATA DO PAGAMENTO DO ACORDO | AS2: VALOR DO DEPÓSITO RECURSAL | AT2: VALOR HOMOLOGADO PELO JUÍZO | AU2: DE QUEM FORAM OS CÁLCULOS HOMOLOGADOS? | AV2: DIFERENÇA DE VALOR DISCUTIDO | AW2: ESOCIAL | AX2: DATA DO ÚLTIMO ANDAMENTO | AY2: ANDAMENTO
A3: 44176 | B3: 2 | C3: 1001370-57.2020.5.02.0020 | D3: LUCENIR SANTOS MOREIRA | E3: MARTINS & FERNANDES ADVOGADOS ASSOCIADOS | F3: CARGOX AGENCIADORA DE SERVIÇOS E CARGAS LTDA | G3: N/A | H3: TRABALHISTA | I3: EX-EMPREGADO | J3: EXECUTIVO DE OPERAÇÕES DE GRANDES CONTAS III | K3: RECURSAL | L3: AGUARDANDO JULGAMENTO DO AGRAVO DE INSTRUMENTO | M3: PROVÁVEL | N3: 20ª VARA DO TRABALHO DE SÃO PAULO | O3: TST | P3: SÃO PAULO/SP | Q3: Descaracterização do cargo de confiança; Horas extras R$ 136.060,00; Intervalo intrajornada R$ 91.220,00; Multa normativa R$ 500,00; Honorários de sucumbência R$ 22.778,00 e Gratuidade de justiça. | R3: O depoimento do preposto reforça que a reclamante, no cargo de supervisora, exercia funções típicas de gestão (contratação, demissão, férias, aprovação de horas extras), o que pode enquadrá-la em cargo de confiança, afastando o direito às horas extras. Além disso, ficou registrado que havia orientação para jornada de 8 horas em home office, sem controle formal, o que enfraquece a tese da reclamante de sobrecarga sistemática. | S3: 44782 | T3: LEANDRO OLIVEIRA LIMA | U3: DANILO CRESPILHO CORREIA; LUAN CAMILO PEREIRA MENDIETA | V3: RAFAEL RODRIGUES; WILLIAN KACZMARECK FITIPALDI | W3: NÃO HÁ PEDIDO | X3: N/A | Y3: DESFAVORÁVEL | Z3: RITA DE CASSIA MARTINEZ | AA3: 45257 | AB3: Embora a sentença tenha reconhecido alguns pontos favoráveis à empresa (como a exclusão do cargo de confiança, indeferimento da justiça gratuita e compensações), houve condenação significativa em horas extras e intervalos, elevando o valor da condenação. | AC3: DESFAVORÁVEL | AD3: ANA MARIA MORAES BARBOSA MACEDO | AE3: 10ª | AF3: 45502 | AG3: O Tribunal reconheceu que os cartões de ponto apresentados pela empresa são válidos. Excluiu da condenação o pagamento de horas extras por supressão de intervalo intrajornada nesse período. O Tribunal destacou que o art. 62, II, da CLT não exige obrigatoriamente gratificação de 40% para caracterizar cargo de confiança. O Tribunal declarou a invalidade do sistema de compensação adotado pela empresa, por ausência de requisitos formais previstos nas convenções coletivas (assinaturas, ajustes com sindicato, controles assinados). - Mantida a condenação ao pagamento de diferenças de horas extras e reflexos referentes ao período em que o banco de horas foi considerado irregular. | AH3: AGUARDANDO | AI3: SERGIO PINTO MARTINS | AJ3: 8ª | AK3: N/A | AL3: N/A | AM3: 227780 | AN3: 100000 | AO3: 0 | AP3: 0 | AQ3: 0 | AR3: N/A | AS3: 64361.9 | AT3: 0 | AU3: N/A | AV3: 0 | AW3: N/A | AX3: 45961 | AY3: O reclamante apresentou manifestação requerendo a inclusão do processo em pauta para julgamento.
A4: 44805 | B4: 2 | C4: 1001244-93.2022.5.02.0001 | D4: LEANDRO DE OLIVEIRA SANTOS | E4: MARTINS & FERNANDES ADVOGADOS ASSOCIADOS | F4: CARGOX AGENCIADORA DE SERVIÇOS E CARGAS LTDA | G4: N/A | H4: TRABALHISTA | I4: EX-EMPREGADO | J4: EXECUTIVO DE OPERAÇÕES DE CLIENTES POTENCIAIS I | K4: RECURSAL | L4: AGUARDANDO JULGAMENTO DO AGRAVO DE INSTRUMENTO | M4: PROVÁVEL | N4: 1ª VARA DO TRABALHO DE SÃO PAULO | O4: TST | P4: SÃO PAULO/SP | Q4: Horas extras R$ 65.466,00; Nulidade do banco de horas; Intervalo intrajornada R$ 37.623,00; Multa normativa R$ 500,00; Honorários de sucumbência e Gratuidade de justiça. | R4: Foi realizada a oitiva das partes e de suas testemunhas, cujo conteúdo encontra-se devidamente degravado nos autos. | S4: 45119 | T4: LEANDRO OLIVEIRA LIMA | U4: LEANDRO DOS SANTOS ARAUJO | V4: EDER ENRIQUE ARRIAGADA BIANCIOTTO | W4: NÃO HÁ PEDIDO | X4: N/A | Y4: DESFAVORÁVEL | Z4: TATIANA AGDA JULIA ELENICE HELENA BELOTI MARANESI ARROYO | AA4: 45163 | AB4: A sentença foi desfavorável à Cargox, pois reconheceu: Jornada extensa e condenação em horas extras com reflexos. Supressão parcial do intervalo intrajornada. Por outro lado, houve pontos favoráveis à defesa: Indeferimento das multas normativas. | AC4: DESFAVORÁVEL | AD4: SONIA MARIA FORSTER DO AMARAL | AE4: 2ª | AF4: 45376 | AG4: Foram mantidas condenações em horas extras, intervalo intrajornada e reflexos, que continuam a representar impacto financeiro | AH4: AGUARDANDO | AI4: JOÃO PEDRO SILVESTRIN | AJ4: 8ª | AK4: N/A | AL4: N/A | AM4: 103589 | AN4: 100000 | AO4: 0 | AP4: 0 | AQ4: 0 | AR4: N/A | AS4: 50660.56 | AT4: 0 | AU4: N/A | AV4: 0 | AW4: N/A | AX4: 46119 | AY4: Processo em trâmite no TST, distribuído para apreciação do agravo de instrumento interposto pela reclamada.
A5: 44984 | B5: 2 | C5: 1000255-97.2023.5.02.0051 | D5: GUSTAVO PAROLINI | E5: A.S. AZEVEDO SOCIEDADE DE ADVOGADOS | F5: FRETEBRAS INTERNET E SERVIÇOS LTDA | G5: N/A | H5: TRABALHISTA | I5: EX-EMPREGADO | J5: EXECUTIVO COMERCIAL GRANDES CONTAS II | K5: RECURSAL | L5: AGUARDANDO JULGAMENTO DO AGRAVO INTERNO | M5: PROVÁVEL | N5: 51ª VARA DO TRABALHO DE SÃO PAULO | O5: TST | P5: SÃO PAULO/SP | Q5: Bônus R$ 31.790,47; FGTS; Devolução proporcional; Verbas rescisórias R$ 42.944,25; Multa do art. 477 da CLT R$ 12.938,40; Multa do art. 467 da CLT R$ 16.631,07; Honorários de sucumbência e Gratuidade de justiça. | R5: Considerando que os pedidos formulados pelo reclamante estão amparados em prova documental, foi dispensada a colheita dos depoimentos pessoais. | S5: 45097 | T5: KAUÊ SANTOS | U5: N/A | V5: N/A | W5: NÃO HÁ PEDIDO | X5: N/A | Y5: DESFAVORÁVEL | Z5: VIVIANY APARECIDA CARREIRA MOREIRA RODRIGUES | AA5: 18/092023 | AB5: A sentença foi parcialmente desfavorável à Fretebras, pois: Reconheceu a natureza salarial do bônus de retenção e condenou a empresa ao pagamento de diferenças rescisórias e FGTS. Julgou improcedente a reconvenção, afastando a tese de saldo devedor do reclamante. Por outro lado, houve pontos favoráveis à defesa: Reflexos do bônus foram limitados (não incidem em férias, 13º ou DSR). Multas dos arts. 467 e 477 foram rejeitadas. | AC5: FAVORÁVEL | AD5: JORGE EDUARDO ASSAD | AE5: 1ª | AF5: 45546 | AG5: O acórdão foi parcialmente favorável à Fretebras: Confirmou a validade da cláusula de devolução do bônus e limitou seus reflexos. Indeferiu justiça gratuita ao reclamante. Rejeitou multas da CLT. Por outro lado, manteve a condenação da empresa ao pagamento de diferenças rescisórias e FGTS proporcional. | AH5: FAVORÁVEL | AI5: AMAURY RODRIGUES PINTO JUNIOR | AJ5: 1ª | AK5: 45931 | AL5: A decisão foi favorável à Fretebras, pois: O TST manteve a validade da cláusula de devolução proporcional do bônus de retenção. Rejeitou as alegações do reclamante sobre nulidade contratual, justiça gratuita e multas da CLT. Confirmou que não cabia reexame de provas, consolidando a vitória da empresa nesse ponto. | AM5: 94622.09 | AN5: 8000 | AO5: 0 | AP5: 0 | AQ5: 0 | AR5: N/A | AS5: 8000 | AT5: 0 | AU5: N/A | AV5: 0 | AW5: N/A | AX5: 46129 | AY5: Interposto agravo interno pelo reclamante, com contraminuta apresentada pela reclamada, o feito aguarda apreciação pelo órgão julgador.
A6: 45008 | B6: 2 | C6: 1000392-52.2023.5.02.0060 | D6: MAYCON DE ARAUJO BIZERRA | E6: ANGELA PEREZ ADVOGADOS | F6: CARGOX AGENCIADORA DE SERVIÇOS E CARGAS LTDA | G6: N/A | H6: TRABALHISTA | I6: EX-EMPREGADO | J6: ANALISTA DE OPERACAO I | K6: RECURSAL | L6: AGUARDANDO JULGAMENTO DO AGRAVO INTERNO | M6: PROVÁVEL | N6: 60ª VARA DO TRABALHO DE SÃO PAULO | O6: TST | P6: SÃO PAULO/SP | Q6: Horas extras R$ 21.972,40; Feriados e folgas R$ $ 4.051,84; Honorários de sucumbência e Gratuidade de justiça | R6: A audiência foi positiva para a empresa, pois o depoimento do preposto sustentou a tese de jornada regular e compensação via banco de horas, enquanto a prova testemunhal da parte contrária mostrou contradições e fragilidades. | S6: 45071 | T6: LEANDRO OLIVEIRA LIMA | U6: N/A | V6: LEANDRO MIRANDA DE SOUSA | W6: NÃO HÁ PEDIDO | X6: N/A | Y6: DESFAVORÁVEL | Z6: JERONIMO AZAMBUJA FRANCO NETO | AA6: 45104 | AB6: O juiz reconheceu a validade dos cartões de ponto no período presencial, o que limita a condenação apenas ao período de home office. Não houve reconhecimento de supressão de intervalo intrajornada nem de labor em feriados, reduzindo o impacto da condenação. Autorizada a dedução de valores já pagos sob o mesmo título, evitando duplicidade. Condenação em horas extras no período de home office, com reflexos amplos. Condenação em FGTS + 40% sobre as parcelas deferidas. | AC6: DESFAVORÁVEL | AD6: RICARDO ARTUR COSTA E TRIGUEIROS | AE6: 4ª | AF6: 45196 | AG6: O Tribunal reconheceu que não houve supressão de intervalo intrajornada, afastando esse ponto da discussão. Mantida a condenação em horas extras durante o home office, com reflexos em DSR, férias, 13º, FGTS e aviso prévio. | AH6: AGUARDANDO | AI6: SERGIO PINTO MARTINS | AJ6: 8ª | AK6: N/A | AL6: N/A | AM6: 26024.24 | AN6: 20000 | AO6: 0 | AP6: 0 | AQ6: 0 | AR6: N/A | AS6: 20000 | AT6: 0 | AU6: N/A | AV6: 0 | AW6: N/A | AX6: 45541 | AY6: O feito encontra-se em trâmite no TST, pendente de apreciação do agravo de instrumento interposto pela reclamada.
A7: 45027 | B7: 2 | C7: 1000495-68.2023.5.02.0057 | D7: MARIA APARECIDA SOLLA | E7: RODRIGUES & MIRANDA ADVOGADOS ASSOCIADOS | F7: FRETEBRAS INTERNET E SERVIÇOS LTDA | G7: N/A | H7: TRABALHISTA | I7: EX-EMPREGADO | J7: ANALISTACOMERCIALIII | K7: RECURSAL | L7: AGUARDANDO JULGAMENTO DO AGRAVO INTERNO | M7: REMOTO | N7: 57ª VARA DO TRABALHO DE SÃO PAULO | O7: TST | P7: SÃO PAULO/SP | Q7: Horas extras R$ 48.174,00; Intervalo intrajornada R$ 23.955,00; Equiparação salarial R$ 71.666,00; DRS R$ 7.600,00; Honorários de sucumbência R$ 15.139,00 e Gratuidade de justiça. | R7: Testemunha da reclamada foi aceita e compromissada, reforçando a versão da empresa. Depoimento confirma que havia jornada regular (9h–18h), sem sobrecarga, e que o trabalho era acompanhado por métricas e ferramentas digitais. Ficou registrado que a diferença entre a reclamante e a paradigma Amanda estava apenas no perfil dos clientes, não em desigualdade de funções. Indeferimento da testemunha de contraprova da reclamante evita produção de prova adicional contra a empresa. | S7: 45190 | T7: LEANDRO OLIVEIRA LIMA | U7: RENAN RODRIGUES RONCHI | V7: N/A | W7: NÃO HÁ PEDIDO | X7: N/A | Y7: DESFAVORÁVEL | Z7: LUCIANA BEZERRA DE OLIVEIRA | AA7: 45293 | AB7: A sentença foi parcialmente favorável à reclamante, com condenação relevante em diferenças salariais e horas extras. Contudo, a empresa obteve êxito em afastar pontos importantes (DSR sobre comissões, art. 384 da CLT e litigância de má-fé), o que reduziu o impacto da condenação. O ponto mais crítico para a defesa é o reconhecimento da equiparação salarial e da jornada controlável em teletrabalho, que fundamentaram a maior parte da condenação. | AC7: FAVORÁVEL | AD7: MARIA DE LOURDES ANTONIO | AE7: 17ª | AF7: 45601 | AG7: A decisão foi plenamente favorável à Fretebras, que conseguiu reverter a condenação inicial e obteve a improcedência total da ação. | AH7: FAVORÁVEL | AI7: AMAURY RODRIGUES PINTO JUNIOR | AJ7: 1ª | AK7: 45917 | AL7: A decisão do TST foi plenamente favorável à Fretebras, garantindo a manutenção da improcedência da ação e encerrando o processo em definitivo sem condenação contra a empresa. | AM7: 166534 | AN7: 0 | AO7: 0 | AP7: 0 | AQ7: 0 | AR7: N/A | AS7: 12665.14 | AT7: 0 | AU7: N/A | AV7: 0 | AW7: N/A | AX7: 45958 | AY7: O reclamante interpôs agravo interno, tendo a reclamada apresentado contraminuta, encontrando-se o recurso pendente de julgamento.
A8: 45056 | B8: 2 | C8: 1000637-34.2023.5.02.0005 | D8: GISELE BRITO COSTA | E8: LUCIO FLAVIO XAVIER DA SILVA | F8: FRETEBRAS INTERNET E SERVIÇOS LTDA | G8: N/A | H8: TRABALHISTA | I8: EX-EMPREGADO | J8: ANALISTA COMERCIAL II | K8: RECURSAL | L8: AGUARDANDO JULGAMENTO DO AGRAVO DE PETIÇÃO | M8: PROVÁVEL | N8: 5ª VARA DO TRABALHO DE SÃO PAULO | O8: 2ª | P8: SÃO PAULO/SP | Q8: Horas extras R$ 102.764,63; Equiparação salarial R$ 49.431,00; Honorários de sucumbência e Gratuidade de justiça. | R8: A audiência trouxe contradições nas testemunhas da reclamante, enquanto as testemunhas da empresa reforçaram a diferença de funções entre a reclamante e Amanda, além da ausência de controle formal de jornada. Isso fortalece a defesa da Fretebras contra pedidos de equiparação salarial e horas extras. | S8: 45126 | T8: LEANDRO OLIVEIRA LIMA | U8: VICTOR AMADEU MARIANO; MYLENA SOUSA GIRARDI | V8: SAMANTA ALVES VASCONCELOS YACOB SILVEIRA | W8: NÃO HÁ PEDIDO | X8: N/A | Y8: DESFAVORÁVEL | Z8: CARLOS EDUARDO FERREIRA DE SOUZA DUARTE SAAD | AA8: 45160 | AB8: A sentença foi parcialmente favorável à Fretebras, pois afastou a equiparação salarial e reconheceu contradições nas provas da reclamante, mas manteve condenação significativa em horas extras | AC8: DESFAVORÁVEL | AD8: ARMANDO AUGUSTO PINHEIRO PIRES | AE8: 10ª | AF8: 45437 | AG8: O acórdão foi parcialmente favorável à reclamante e desfavorável à Fretebras, pois manteve a condenação em horas extras e a expedição de ofício ao MPF. A empresa conseguiu afastar definitivamente a equiparação salarial, mas não obteve êxito em reduzir a condenação principal. | AH8: N/A | AI8: N/A | AJ8: N/A | AK8: N/A | AL8: N/A | AM8: 153000 | AN8: 50000 | AO8: 94777.61 | AP8: 70248.7 | AQ8: 0 | AR8: N/A | AS8: 96269.6 | AT8: 90784.12 | AU8: RECLAMANTE | AV8: 20535.42 | AW8: N/A | AX8: 46078 | AY8: Com o trânsito em julgado da ação, iniciou-se a fase de execução, ocasião em que as partes apresentaram seus cálculos, sendo homologados os cálculos da reclamante. A reclamada opôs embargos à execução, que foram julgados parcialmente procedentes, com correções relevantes que reduziram a base de cálculo (exclusão da duplicidade em DSR e aplicação da Súmula 340 do TST quanto às horas extras sobre comissões). Manteve-se, entretanto, a aplicação da taxa SELIC da Receita Federal. Ambas as partes interpuseram agravo de petição e apresentaram contraminutas. Foi determinada a liberação dos valores incontroversos em favor da reclamante, permanecendo pendente apenas a discussão sobre os valores controvertidos. O processo foi distribuído ao TRT da 2ª Região para julgamento dos agravos, sob relatoria da Desembargadora Luciana Maria Bueno Camargo de Magalhães, na 10ª Turma.
A9: 45153 | B9: 2 | C9: 1001217-34.2023.5.02.0015 | D9: CICERO RAMON SANTOS ALVES | E9: RODRIGUES & MIRANDA ADVOGADOS ASSOCIADOS | F9: FRETEBRAS INTERNET E SERVIÇOS LTDA | G9: N/A | H9: TRABALHISTA | I9: EX-EMPREGADO | J9: ANALISTA COMERCIAL III | K9: RECURSAL | L9: AGUARDANDO JULGAMENTO DO AGRAVO DE INSTRUMENTO | M9: PROVÁVEL | N9: 15ª VARA DO TRABALHO DE SÃO PAULO | O9: TST | P9: SÃO PAULO/SP | Q9: Horas extras R$ 30.519,00; Intervalo intrajornada R$ 16.650,00; DSR R$ 5.225,00; Equiparação salarial R$ 119.225,00; Honorários de sucumbência R$ 17.166,00 e Gratuidade de justiça. | R9: O preposto e a testemunha confirmaram a diferença de complexidade entre as carteiras, o que enfraquece o pedido de equiparação salarial. Ficou registrado que não havia controle formal de jornada, apenas ferramentas de login, o que reforça a tese de teletrabalho sem fiscalização direta. A testemunha do reclamante foi fragilizada pela amizade íntima e ação própria contra a empresa, reduzindo sua credibilidade. | S9: 45607 | T9: BIANCA GIULIA POLASTRINI DE LIMA | U9: RAFAEL ALVES FERREIRA SANTOS | V9: FABIO RODRIGO FERREIRA DE OLIVEIRA | W9: NÃO HÁ PEDIDO | X9: N/A | Y9: DESFAVORÁVEL | Z9: CLAUDIA TEJEDA COSTA | AA9: 45681 | AB9: A sentença foi desfavorável à Fretebras, pois reconheceu: Equiparação salarial com paradigmas. Horas extras e indenização pelo intervalo intrajornada. Por outro lado, houve pontos favoráveis à defesa: Improcedência do pedido de DSR sobre comissões. Reconhecimento da sucumbência recíproca, com honorários também em favor da reclamada. | AC9: DESFAVORÁVEL | AD9: MARTA CASADEI MOMEZZO | AE9: 2ª | AF9: 45917 | AG9: O acórdão foi parcialmente favorável à Fretebras: afastada a condenação por equiparação salarial, que representava impacto financeiro elevado. Pontos mantidos contra a empresa: condenação em horas extras e intervalo intrajornada. Pedido do reclamante sobre DSR foi rejeitado, reforçando a correção dos pagamentos da empresa. | AH9: AGUARDANDO | AI9: LUIZ PHILIPPE VIEIRA DE MELLO FILHO | AJ9: N/A | AK9: N/A | AL9: N/A | AM9: 188835 | AN9: 135000 | AO9: 0 | AP9: 0 | AQ9: 0 | AR9: N/A | AS9: 13133.46 | AT9: 0 | AU9: N/A | AV9: 0 | AW9: N/A | AX9: 46083 | AY9: Processo em trâmite no TST, distribuído para apreciação do agravo de instrumento interposto pelo reclamante, estando sob exame da Presidência quanto à admissibilidade recursal.
A10: 45153 | B10: 2 | C10: 1001215-79.2023.5.02.0010 | D10: FABIO RODRIGO FERREIRA DE OLIVEIRA | E10: RODRIGUES & MIRANDA ADVOGADOS ASSOCIADOS | F10: FRETEBRAS INTERNET E SERVIÇOS LTDA | G10: N/A | H10: TRABALHISTA | I10: EX-EMPREGADO | J10: ANALISTA COMERCIAL I | K10: EXECUÇÃO | L10: INÍCIO DA EXECUÇÃO | M10: REMOTO | N10: 10ª VARA DO TRABALHO DE SÃO PAULO | O10: 1ª | P10: SÃO PAULO/SP | Q10: Horas extras R$ 27.518,00; Intervalo intrajornada R$ 13.755; Equiparação salarial R$ 110.883,00; DSR R$ 3.200,00; Honorários de sucumbência R$ 15.535,00 e Gratuidade de justiça. | R10: A audiência foi equilibrada, mas trouxe pontos positivos para a Fretebras, já que a contradita contra sua testemunha foi rejeitada e a instrução foi encerrada sem prejuízo à defesa. Agora, o processo segue para julgamento em novembro. | S10: 45222 | T10: LEANDRO OLIVEIRA LIMA | U10: BIANCA MARCOS DODI | V10: MARCELLY CRISTINE FERREIRA DE SILVA | W10: NÃO HÁ PEDIDO | X10: N/A | Y10: FAVORÁVEL | Z10: MARINA DE ALMEIDA AOKI | AA10: 45287 | AB10: A decisão foi amplamente favorável à Fretebras, com improcedência total dos pedidos do reclamante e condenação em honorários advocatícios. | AC10: FAVORÁVEL | AD10: SONIA MARIA DE BARROS | AE10: 7ª | AF10: 45426 | AG10: O acórdão foi plenamente favorável à Fretebras, consolidando a improcedência total dos pedidos do reclamante e reforçando a tese defensiva da empresa. | AH10: FAVORÁVEL | AI10: AMAURY RODRIGUES PINTO JUNIOR | AJ10: 1ª | AK10: 45684 | AL10: o TST encerrou a discussão mantendo a improcedência total dos pedidos do reclamante. A Fretebras obteve vitória definitiva, com a decisão transitando em julgado em favor da empresa. | AM10: 170891 | AN10: 0 | AO10: 0 | AP10: 0 | AQ10: 0 | AR10: N/A | AS10: 0 | AT10: 0 | AU10: N/A | AV10: 0 | AW10: N/A | AX10: 45967 | AY10: O TST negou provimento ao agravo de instrumento do reclamante em recurso de revista. Em seguida, o agravo interno interposto também foi rejeitado. Diante da ausência de novos recursos, ocorreu o trânsito em julgado da demanda.
A11: 45271 | B11: 2 | C11: 1001831-24.2023.5.02.0020 | D11: LUCENIR SANTOS MOREIRA | E11: MARTINS & FERNANDES ADVOGADOS ASSOCIADOS | F11: CARGOX AGENCIADORA DE SERVIÇOS E CARGAS LTDA | G11: N/A | H11: TRABALHISTA | I11: EX-EMPREGADO | J11: EXECUTIVO DE OPERAÇÕES DE GRANDES CONTAS III | K11: EXECUÇÃO | L11: AGUARDANDO ARQUIVAMENTO | M11: REMOTO | N11: 20ª VARA DO TRABALHO DE SÃO PAULO | O11: 1ª | P11: SÃO PAULO/SP | Q11: Cumprimento de sentença | R11: N/A | S11: N/A | T11: N/A | U11: N/A | V11: N/A | W11: N/A | X11: N/A | Y11: N/A | Z11: N/A | AA11: N/A | AB11: N/A | AC11: N/A | AD11: N/A | AE11: N/A | AF11: N/A | AG11: N/A | AH11: N/A | AI11: N/A | AJ11: N/A | AK11: N/A | AL11: N/A | AM11: 430527.7 | AN11: 125339.69 | AO11: 353573.33 | AP11: 252775 | AQ11: 0 | AR11: N/A | AS11: 221092.51 | AT11: 192346.64 | AU11: PERITO | AV11: 161226.69 | AW11: N/A | AX11: 46094 | AY11: Iniciada a execução provisória pela reclamante, a reclamada requereu o parcelamento da execução, pedido que foi deferido. Já consta nos autos a comprovação do pagamento da 6ª parcela e, atualmente, o processo encontra-se em fase final, aguardando apenas o arquivamento.
A12: 45279 | B12: 2 | C12: 1001955-81.2023.5.02.0060 | D12: CAMILA REBEQUI | E12: RODRIGUES & MIRANDA ADVOGADOS ASSOCIADOS | F12: FRETEBRAS INTERNET E SERVIÇOS LTDA | G12: N/A | H12: TRABALHISTA | I12: EX-EMPREGADO | J12: ANALISTA COMERCIAL II | K12: EXECUÇÃO | L12: AGUARDANDO INÍCIO DA EXECUÇÃO | M12: PROVÁVEL | N12: 60ª VARA DO TRABALHO DE SÃO PAULO | O12: 1ª | P12: SÃO PAULO/SP | Q12: Horas extras R$ 55.005; Intervalo intrajornada R$ 29.926,00; DSR R$ 19.550,00; Equiparação salarial R$ 81.539,00; Honorários de sucumbência R$ 18.602,00 e Gratuidade de justiça. | R12: O preposto e a testemunha confirmaram que a reclamante não era “key account”, atendendo clientes de menor porte e complexidade, o que enfraquece o pedido de equiparação salarial. Ficou registrado que não havia controle formal de jornada até março/2023, reforçando a tese de teletrabalho sem fiscalização direta. O depoimento da testemunha da reclamante foi genérico e pouco consistente, reduzindo sua força probatória. | S12: 45415 | T12: LEANDRO OLIVEIRA LIMA | U12: RAFAEL ALVES FERREIRA SANTOS | V12: MARIANA PINTO GONÇALVES | W12: NÃO HÁ PEDIDO | X12: N/A | Y12: DESFAVORÁVEL | Z12: LETICIA NETO AMARAL | AA12: 45530 | AB12: Foram rejeitados os pedidos de equiparação salarial e reflexos de comissão em DSR, além de afastada a tese de diferenças de horas extras no período com ponto registrado. Contudo, houve condenação ao pagamento de horas extras e da supressão parcial do intervalo intrajornada, o que gera impacto financeiro. | AC12: DESFAVORÁVEL | AD12: MAGDA CARDOSO MATEUS SILVA | AE12: 3ª | AF12: 45707 | AG12: O acórdão foi desfavorável à empresa, pois confirmou a condenação ao pagamento de horas extras e da indenização pelo intervalo intrajornada. Por outro lado, foi favorável em parte, já que manteve a improcedência dos pedidos da reclamante sobre equiparação salarial, reflexos em DSR e horas extras no período com ponto registrado | AH12: DESFAVORÁVEL | AI12: ALEXANDRE LUIZ RAMOS | AJ12: 4ª | AK12: 45926 | AL12: A decisão foi desfavorável à Fretebras, pois confirmou a condenação mantida pelo TRT-2 (horas extras e intervalo intrajornada). Contudo, foi favorável em parte, já que também rejeitou os pedidos adicionais da reclamante (equiparação salarial, reflexos em DSR e horas extras no período com ponto registrado). | AM12: 204622 | AN12: 25000 | AO12: 0 | AP12: 0 | AQ12: 0 | AR12: N/A | AS12: 25000 | AT12: 0 | AU12: N/A | AV12: 0 | AW12: N/A | AX12: 46130 | AY12: As partes interpuseram agravo interno, ao qual foi negado provimento. A decisão manteve a condenação da Fretebras ao pagamento de horas extras e da indenização pela supressão parcial do intervalo intrajornada. Contudo, foi parcialmente favorável à empresa, pois rejeitou os pedidos da reclamante relativos à equiparação salarial e à alegada nulidade processual. Diante da ausência de interposição de recurso por ambas as partes, ocorreu o trânsito em julgado, aguardando-se o início da execução.
A13: 45291 | B13: 9 | C13: 0000894-03.2023.5.09.0322 | D13: ALINE INACIO DA SILVA | E13: F CRUZ ADVOCACIA | F13: CARGOX AGENCIADORA DE SERVIÇOS E CARGAS LTDA | G13: FABIANO PEREIRA BRASILIO (1ª reclamada); CORAL TRANSPORTES LTDA (2ª reclamada); NOVA COR TRANSPORTES LTDA (4ª reclamada) | H13: TRABALHISTA | I13: TERCEIRO | J13: AUXILIAR ADMINISTRATIVO | K13: CONHECIMENTO | L13: SOBRESTADO - TEMA .1389 | M13: POSSÍVEL | N13: 02ª VARA DO TRABALHO DE PARANAGUÁ | O13: 1ª | P13: PARANAGUÁ/PR | Q13: Responsabilidade subsidiária da Frete; Reconhecimento de vínculo de emprego; Verbas rescisórias; Multa do art. 467 da CLT; Multa do art. 477 da CLT; Horas extras; FGTS; Multa de 40% do FGTS; Indenização por dano moral R$ 10.000,00; Honorários de sucumbência e Gratuidade de justiça. | R13: N/A | S13: N/A | T13: N/A | U13: N/A | V13: N/A | W13: N/A | X13: N/A | Y13: N/A | Z13: N/A | AA13: N/A | AB13: N/A | AC13: N/A | AD13: N/A | AE13: N/A | AF13: N/A | AG13: N/A | AH13: N/A | AI13: N/A | AJ13: N/A | AK13: N/A | AL13: N/A | AM13: 25322.56 | AN13: 0 | AO13: 0 | AP13: 0 | AQ13: 0 | AR13: N/A | AS13: 0 | AT13: 0 | AU13: N/A | AV13: 0 | AW13: N/A | AX13: 45826 | AY13: Na audiência inaugural, foi determinado o sobrestamento do processo em razão da pendência de julgamento do Tema de Repercussão Geral nº 1.389.
A14: 45306 | B14: 16 | C14: 0016045-64.2024.5.16.0003 | D14: QLIVHYA HADHAYA VIEIRA MOREIRA | E14: VIEIRA OLIVEIRA ADVOGADOS ASSOCIADOS | F14: FRETEBRAS INTERNET E SERVIÇOS LTDA | G14: EBS2 TRADE E GESTAO LTDA | H14: TRABALHISTA | I14: TERCEIRO | J14: PROMOTORA DE VENDAS | K14: EXECUÇÃO | L14: INÍCIO DA EXECUÇÃO | M14: PROVÁVEL | N14: 3ª VARA DO TRABALHO DE SÃO LUÍS | O14: 1ª | P14: SÃO LUÍS/MA | Q14: Responsabilidade subsidiária; Indenização prevista no art. 479 da CLT R$ 1.805,14; Comissões R$ 526,88; INSS R$ 179,45; Indenização do art. 17 da CLT R$ 2.780,16; Contribuição sindical R$ 90,25; Intervalo intrajornada R$ 36.102,80; Indenização por dano moral R$ 90.257,00; Multa do art. 467 da CLT R$ 1.899,81; Multa do art. 477 da CLT R$ 1.805,14; Multa normativa R$ 2.973,28; Estabilidade gestante R$ 9.025,70; Honorários de sucumbência e Gratuidade de justiça | R14: Houve depoimento do preposto da EBS2, que confirmou vínculo da reclamante entre fevereiro e agosto de 2023, sem pagamento de comissões e com jornada regular. Testemunha da reclamante relatou experiência semelhante na função de promotora de vendas, mencionando metas e pagamento de comissões “por fora”, mas não soube confirmar se a reclamante recebia. A instrução foi encerrada, sem outras provas a produzir. | S14: 45497 | T14: ULIO CESAR FRANCO LEITE | U14: N/A | V14: PRISCILA MARIA VEIGAS MAGALHÃES | W14: NÃO HÁ PEDIDO | X14: N/A | Y14: DESFAVORÁVEL | Z14: NUBIA PRAZERES PINHEIRO | AA14: 45565 | AB14: Principais pedidos da reclamante (estabilidade gestante, indenização do art. 479 da CLT, integração de comissões, danos morais, multas rescisórias e convencionais, intrajornada) foram julgados improcedentes. O único pedido acolhido foi a devolução de desconto previdenciário indevido, no valor de R$ 179,45, referente ao INSS. | AC14: FAVORÁVEL | AD14: JAMES MAGNO ARAUJO FARIAS | AE14: 2ª | AF14: 45929 | AG14: O acórdão foi plenamente favorável, pois confirmou a sentença que rejeitou todos os pedidos relevantes da reclamante, mantendo apenas a condenação subsidiária de pequeno valor (R$ 179,45). | AH14: N/A | AI14: N/A | AJ14: N/A | AK14: N/A | AL14: N/A | AM14: 149452.33 | AN14: 179.45 | AO14: 0 | AP14: 0 | AQ14: 0 | AR14: N/A | AS14: 0 | AT14: 0 | AU14: N/A | AV14: 0 | AW14: N/A | AX14: 46083 | AY14: Com a abertura da liquidação, a reclamante apresentou requerimento de cumprimento da sentença em face da 1ª ré, o qual aguarda apreciação.
A15: 45357 | B15: 5 | C15: 0000239-95.2024.5.05.0196 | D15: TAHYNAR DE JESUS DA CONCEICAO SANTOS | E15: NA MARIA DE SOUZA BATISTA NASCIMENTO | F15: FRETEBRAS INTERNET E SERVIÇOS LTDA | G15: EBS2 TRADE E GESTAO LTDA | H15: TRABALHISTA | I15: TERCEIRO | J15: PROMOTORA DE VENDAS | K15: EXECUÇÃO | L15: AGUARDANDO ARQUIVAMENTO | M15: REMOTO | N15: 6ª VARA DO TRABALHO DE FEIRA DE SANTANA | O15: 1ª | P15: FEIRA DE SANTANA/BA | Q15: Responsabilidade subsidiária; Estabilidade gestante; Salários devidos R$ 23.040,00; Salário-família R$ 819,54; 13º salário R$ 533,33; Vale refeição R$ 5.880,00; Férias R$ 3.377,77; Aviso-prévio R$ 1.600,00; FGTS R$ 1.408,00; Multa de 40% R$ 972,80; INSS R$ 1.330,20; Multa do art. 467 da CLT R$ 16.166,48; Indenização por dano moral R$ 10.000,00; Honorários de sucumbência e Gratuidade de justiça. | R15: Foi realizada a oitiva das partes, e a ata foi reconhecida como documento hábil para a liberação do FGTS junto à Caixa Econômica Federal, suprindo a ausência do TRCT e da chave de conectividade. | S15: 45545 | T15: MIRELA LUIZE DE QUEIROZ DOS SANTOS | U15: N/A | V15: N/A | W15: NÃO HÁ PEDIDO | X15: N/A | Y15: DESFAVORÁVEL | Z15: INGRID HEIDI OLIVA BONESS | AA15: 45603 | AB15: embora o pedido de dano moral e algumas multas tenham sido rejeitados, o reconhecimento da estabilidade gestante gerou condenação significativa, com responsabilidade subsidiária da 2ª ré. | AC15: FAVORÁVEL | AD15: LUIS CARLOS GOMES CARNEIRO FILHO | AE15: 5ª | AF15: 45753 | AG15: O recurso da primeira reclamada (EBS2) foi parcialmente provido. Mantida apenas a responsabilidade subsidiária da segunda reclamada (Fretebras). Excluída integralmente a condenação referente à estabilidade gestante e seus reflexos. Invertida a sucumbência, com ônus para a reclamante. | AH15: N/A | AI15: N/A | AJ15: N/A | AK15: N/A | AL15: N/A | AM15: 42332.97 | AN15: 0 | AO15: 0 | AP15: 0 | AQ15: 0 | AR15: N/A | AS15: 0 | AT15: 0 | AU15: N/A | AV15: 0 | AW15: N/A | AX15: 46098 | AY15: Considerando a improcedência da ação e a ausência de recurso por parte da reclamante, operou-se o trânsito em julgado. Em seguida, foi determinado o levantamento do valor depositado pela 1ª reclamada para garantia recursal. Após a confirmação do levantamento, será ordenado o arquivamento definitivo dos autos.
A16: 45456 | B16: 2 | C16: 1000938-82.2024.5.02.0057 | D16: MARIA APARECIDA SOLLA | E16: RODRIGUES & MIRANDA ADVOGADOS ASSOCIADOS | F16: FRETEBRAS INTERNET E SERVIÇOS LTDA | G16: N/A | H16: TRABALHISTA | I16: EX-EMPREGADO | J16: ANALISTACOMERCIALIII | K16: EXECUÇÃO | L16: AGUARDANDO FINALIZAÇÃO DOS AUTOS PRINCIPAIS | M16: PROVÁVEL | N16: 57ª VARA DO TRABALHO DE SÃO PAULO | O16: 1ª | P16: SÃO PAULO/SP | Q16: Cumprimento de sentença | R16: N/A | S16: N/A | T16: N/A | U16: N/A | V16: N/A | W16: NÃO HÁ PEDIDO | X16: N/A | Y16: N/A | Z16: N/A | AA16: N/A | AB16: N/A | AC16: N/A | AD16: N/A | AE16: N/A | AF16: N/A | AG16: N/A | AH16: N/A | AI16: N/A | AJ16: N/A | AK16: N/A | AL16: N/A | AM16: 126957.39 | AN16: 154766.76 | AO16: 154766.76 | AP16: 116802.12 | AQ16: 0 | AR16: N/A | AS16: 144341.28 | AT16: 154766.76 | AU16: RECLAMANTE | AV16: 37964.64 | AW16: N/A | AX16: 45520 | AY16: Considerando que o juízo homologou os cálculos apresentados pelo reclamante, a reclamada opôs embargos à execução, os quais ainda aguardam julgamento. Em despacho, o juízo determinou que a apreciação dos embargos somente ocorrerá após o retorno dos autos principais.
A17: 45639 | B17: 2 | C17: 1002094-96.2024.5.02.0060 | D17: CAMILA REBEQUI | E17: RODRIGUES & MIRANDA ADVOGADOS ASSOCIADOS | F17: FRETEBRAS INTERNET E SERVIÇOS LTDA | G17: N/A | H17: TRABALHISTA | I17: EX-EMPREGADO | J17: ANALISTA COMERCIAL II | K17: RECURSAL | L17: AGUARDANDO JULGAMENTO DO AGRAVO DE INSTRUMENTO | M17: PROVÁVEL | N17: 60ª VARA DO TRABALHO DE SÃO PAULO | O17: 2ª | P17: SÃO PAULO/SP | Q17: Cumprimento de sentença | R17: N/A | S17: N/A | T17: N/A | U17: N/A | V17: N/A | W17: NÃO HÁ PEDIDO | X17: N/A | Y17: DESFAVORÁVEL | Z17: LETICIA NETO AMARAL | AA17: 45762 | AB17: O juízo entendeu que a sentença de mérito já havia estabelecido os parâmetros de cálculo — divisor 220, observância da evolução e globalidade salarial, dias efetivamente laborados e hora noturna reduzida, quando aplicável. Como não houve determinação expressa para aplicação da Súmula 340 do TST, concluiu-se pela correção dos cálculos apresentados. Diante disso, os embargos foram julgados improcedentes. | AC17: DESFAVORÁVEL | AD17: LIANE MARTINS CASARIN | AE17: 3ª | AF17: 45896 | AG17: o TRT manteve a condenação e rejeitou o agravo da Fretebras, entendendo que os cálculos estavam corretos. | AH17: AGUARDANDO | AI17: N/A | AJ17: N/A | AK17: N/A | AL17: N/A | AM17: 64589.79 | AN17: 82609.98 | AO17: 82609.98 | AP17: 49411.45 | AQ17: 0 | AR17: N/A | AS17: 82609.98 | AT17: 82609.98 | AU17: RECLAMANTE | AV17: 33198.53 | AW17: N/A | AX17: 46129 | AY17: A reclamada interpôs agravo de instrumento, atualmente pendente de julgamento. O reclamante apresentou contrarrazões e contraminuta. Em razão da interposição desse recurso, o processo encontra-se, por ora, pendente de distribuição no âmbito do TST.
A18: 45721 | B18: 2 | C18: 1000324-68.2025.5.02.0081 | D18: BRUNA ALVES DE LIMA | E18: LIMA ADVOGADOS ASSOCIADOS | F18: FRETEBRAS INTERNET E SERVIÇOS LTDA | G18: N/A | H18: TRABALHISTA | I18: EX-EMPREGADO | J18: ANALISTA COMERCIAL II | K18: RECURSAL | L18: AGUARDANDO JULGAMENTO DO RECURSO ORDINÁRIO | M18: POSSÍVEL | N18: 81ª VARA DO TRABALHO DE SÃO PAULO | O18: 2ª | P18: SÃO PAULO/SP | Q18: Horas extras R$ 47.757,55; Comissões R$ 55.576,04; Doença ocupacional; Indenização por dano moral R$ 60.000,00; Pensão mensal vitalícia R$ 742.237,73; Plano de saúde vitalício; Descontos indevidos R$ 2.615,44; Honorários de sucumbência e Gratuidade de justiça. | R18: A audiência trouxe elementos que fortalecem a defesa da Fretebras, especialmente no ponto das comissões, já que ficou comprovada a existência de sistema oficial de apuração e que os pagamentos eram feitos de forma distinta (comissão e DSR). Além disso, a justificativa de desligamento por baixa produtividade reforça a tese empresarial. | S18: 45855 | T18: LEANDRO OLIVEIRA LIMA | U18: GERSON ROTKIS MEI JUNIOR | V18: VAGNER NUNES NICOLI | W18: DOENÇA - FAVORÁVEL | X18: SAUL BORGES CRUZ | Y18: DESFAVORÁVEL | Z18: EUDIVAN BATISTA DE SOUZA | AA18: 45904 | AB18: A sentença foi parcialmente favorável à Fretebras, afastando pedidos relevantes (plano de saúde e contribuição assistencial), mas manteve condenações expressivas em comissões, horas extras e doença ocupacional. | AC18: AGUARDANDO | AD18: GABRIEL LOPES COUTINHO FILHO | AE18: 7ª | AF18: N/A | AG18: N/A | AH18: N/A | AI18: N/A | AJ18: N/A | AK18: N/A | AL18: N/A | AM18: 908186.76 | AN18: 100000 | AO18: 0 | AP18: 0 | AQ18: 0 | AR18: N/A | AS18: 13813.83 | AT18: 0 | AU18: N/A | AV18: 0 | AW18: N/A | AX18: 46029 | AY18: Após a interposição do recurso ordinário pela reclamada, o feito foi regularmente distribuído ao TRT para apreciação.
A19: 45733 | B19: 2 | C19: 1000419-12.2025.5.02.0045 | D19: JESSICA GOUVEIA LUIZ | E19: MELGES & MENEGUETI ADVOGADOS ASSOCIADOS | F19: CARGOX AGENCIADORA DE SERVIÇOS E CARGAS LTDA | G19: N/A | H19: TRABALHISTA | I19: EX-EMPREGADO | J19: ANALISTA DE OPERACOES GRANDES CONTAS II | K19: EXECUÇÃO | L19: AGUARDANDO INTERPOSIÇÃO DE RECURSO | M19: PROVÁVEL | N19: 45ª VARA DO TRABALHO DE SÃO PAULO | O19: 1ª | P19: SÃO PAULO/SP | Q19: Rescisão indireta; Verbas rescisórias R$ 11.666,25; FGTS R$ 2.562,00; Multa de 40% do FGTS R$ 1.024,80; Indenização por dano moral R$ 10.000,00; Multa do art. 477 da CLT R$ 4.575,00; Indenização substitutiva R$ 12.120,55; Honorários de sucumbência R$ 6.292,29 e Gratuidade de justiça. | R19: A reclamante requereu a produção de prova oral relativa ao dano moral, vinculada à saída de emprego anterior. O pedido foi indeferido por se tratar de fato irrelevante, uma vez que as condições de trabalho inserem-se no poder diretivo do empregador. A reclamada, por sua vez, requereu a produção de prova oral acerca da rescisão indireta, o que igualmente foi indeferido por se tratar de matéria estritamente de direito. Protestos da reclamada registrados | S19: 45770 | T19: CAMILA VELASCO DE GODOY | U19: N/A | V19: N/A | W19: NÃO HÁ PEDIDO | X19: N/A | Y19: DESFAVORÁVEL | Z19: JEAN MARCEL MARIANO DE OLIVEIRA | AA19: 45777 | AB19: A sentença foi majoritariamente favorável à empresa, pois afastou os pedidos mais gravosos (rescisão indireta, dano moral, aviso prévio, multa de 40% do FGTS e seguro-desemprego), reconhecendo que a saída se deu por pedido de demissão da reclamante. | AC19: DESFAVORÁVEL | AD19: ADRIANA MARIA BATTISTELLI VARELLIS | AE19: 10ª | AF19: 45881 | AG19: O Tribunal confirmou que a mudança para trabalho presencial é legítima, dentro do poder diretivo. Rescisão indireta afastada, evitando condenação em verbas de dispensa sem justa causa. Danos morais indeferidos, eliminando risco de indenização. Mantida a possibilidade de dedução de valores pagos, evitando duplicidade. | AH19: AGUARDANDO | AI19: N/A | AJ19: N/A | AK19: N/A | AL19: N/A | AM19: 48240.89 | AN19: 3943.83 | AO19: 0 | AP19: 0 | AQ19: 0 | AR19: N/A | AS19: 3943.83 | AT19: 3943.83 | AU19: PERITO | AV19: 0 | AW19: N/A | AX19: 46106 | AY19: Com o trânsito em julgado da ação, foram homologados os cálculos da sentença líquida. A reclamada apresentou embargos à execução, que foram julgados improcedentes, mantendo-se integralmente os cálculos homologados. O único aspecto favorável à Cargox foi a rejeição da condenação por litigância de má-fé. Interposto agravo de petição, a decisão foi parcialmente favorável à empresa, determinando que os valores já pagos no TRCT fossem deduzidos da execução, evitando enriquecimento ilícito da reclamante. Aguarda-se eventual interposição de recurso de revista por qualquer das partes; caso não ocorra, os autos retornarão ao juízo de origem para efetivação do pagamento da execução definitiva.
A20: 45734 | B20: 2 | C20: 1000414-10.2025.5.02.0006 | D20: FERNANDO ROGERIO BARBOSA DE BARROS | E20: ZAMITH ASSESSORIA JURÍDICA | F20: FRETEBRAS INTERNET E SERVIÇOS LTDA | G20: N/A | H20: TRABALHISTA | I20: EX-EMPREGADO | J20: COORDENADOR COMERCIAL | K20: EXECUÇÃO | L20: INÍCIO DA EXECUÇÃO | M20: PROVÁVEL | N20: 6ª VARA DO TRABALHO DE SÃO PAULO | O20: 1ª | P20: SÃO PAULO/SP | Q20: Verbas rescisórias R$ 20.448,96; Multa normativa R$ 146,95; Multa do art. 467 da CLT R$ 11.429,57; Multa do art. 477 da CLT R$ 13.199,78; PLR R$ 5.173,25; Repouso semanal remunerado R$ 32.139,54; FGTS R$ 2.571,17; Multa de 40% do FGTS R$ 1.005,98, Honorários de sucumbência R$ 12.917,28 e Gratuidade de justiça. | R20: Em razão dos pedidos formulados pelo reclamante, as partes optaram por não produzir prova oral. | S20: 45817 | T20: WADSON JONATAS NASCIMENTO MARTINS | U20: N/A | V20: N/A | W20: NÃO HÁ PEDIDO | X20: N/A | Y20: DESFAVORÁVEL | Z20: FERNANDA MIYATA FERREIRA | AA20: 45845 | AB20: A sentença foi parcialmente desfavorável à Fretebras, com condenações em DSR, PLR, devolução de desconto e multa normativa. No entanto, a empresa obteve êxito em afastar multas rescisórias. | AC20: DESFAVORÁVEL | AD20: DANIEL VIEIRA ZAINA SANTOS | AE20: 14ª | AF20: 46000 | AG20: O acórdão foi majoritariamente desfavorável à Fretebras, mantendo condenações relevantes (DSR, PLR, multa normativa e devolução de descontos). | AH20: N/A | AI20: N/A | AJ20: N/A | AK20: N/A | AL20: N/A | AM20: 108794.5 | AN20: 35000 | AO20: 108794.5 | AP20: 0 | AQ20: 0 | AR20: N/A | AS20: 13133.46 | AT20: 0 | AU20: N/A | AV20: 0 | AW20: N/A | AX20: 46121 | AY20: Considerando que nenhuma das partes interpuseram recurso de revista o processo retornou a origem para inicio da execução. Foram apresentados os cálculos pelo reclamante.
A21: 45736 | B21: 4 | C21: 0020318-76.2025.5.04.0103 | D21: LETICIA FONSECA ALLEND | E21: DUARTE + JESKE ADVOGADOS | F21: FRETEBRAS INTERNET E SERVIÇOS LTDA | G21: EXATA TRABALHO TEMPORARIO LTDA | H21: TRABALHISTA | I21: TERCEIRO | J21: PROMOTORA DE VENDAS | K21: CONHECIMENTO | L21: AGUARDANDO CUMPRIMENTO DO ACORDO | M21: REMOTO | N21: 3ª VARA DO TRABALHO DE PELOTAS | O21: 1ª | P21: PELOTAS/RS | Q21: Responsabilidade subsidiária; Horas Extras R$ 23.129,50; Adicional de Periculosidade R$ 22.810,92; Férias R$ 8.456,26; Indenização por dano moral R$ 5.000,00; Honorários de sucumbência e Gratuidade de justiça. | R21: Acordo entre o reclamante e a 1ª ré | S21: 45834 | T21: SIEL GONÇALVES PAIVA | U21: N/A | V21: N/A | W21: NÃO HÁ PEDIDO | X21: N/A | Y21: N/A | Z21: N/A | AA21: N/A | AB21: N/A | AC21: N/A | AD21: N/A | AE21: N/A | AF21: N/A | AG21: N/A | AH21: N/A | AI21: N/A | AJ21: N/A | AK21: N/A | AL21: N/A | AM21: 53366.67 | AN21: 0 | AO21: 0 | AP21: 0 | AQ21: 25000 | AR21: 45848 | AS21: 0 | AT21: 0 | AU21: N/A | AV21: 0 | AW21: N/A | AX21: 46001 | AY21: As reclamadas Exata Trabalho Temporário. e Exata Promoções firmaram acordo solidário com a reclamante no valor de R$ 25.000,00, a ser pago em 10 parcelas de R$ 2.500,00. A Fretebras não assumiu responsabilidade direta no acordo, ficando sua eventual responsabilidade condicionada ao inadimplemento das demais, limitada ao valor do acordo acrescido da cláusula penal.
A22: 45761 | B22: 2 | C22: 1000609-92.2025.5.02.0006 | D22: JOICE GOMES FESTRATIS | E22: LEITE ADVOGADOS | F22: CARGOX AGENCIADORA DE SERVIÇOS E CARGAS LTDA | G22: N/A | H22: TRABALHISTA | I22: EX-EMPREGADO | J22: ASSISTENTE COMERCIAL | K22: EXECUÇÃO | L22: INÍCIO DA EXECUÇÃO | M22: REMOTO | N22: 6ª VARA DO TRABALHO DE SÃO PAULO | O22: 1ª | P22: SÃO PAULO/SP | Q22: Acúmulo de função R$ 48.604,03; Horas extras R$ 56.327,57; Intervalo intrajornada R$ 4.191,81; Honorários de sucumbência e Gratuidade de justiça. | R22: A audiência foi conduzida de forma equilibrada, com ambas as partes apresentando depoimentos e testemunhas por degravação. | S22: 45799 | T22: SAMUEL LISBOA GOMES | U22: FERNANADA SAGUINI DE ANDRADE | V22: TATIANE DE SOUSA CARVALHO | W22: NÃO HÁ PEDIDO | X22: N/A | Y22: FAVORÁVEL | Z22: LUCIANA SIQUEIRA ALVES GARCIA | AA22: 45810 | AB22: A sentença foi plenamente favorável à Cargox, com improcedência total da reclamação trabalhista e absolvição da empresa de todas as acusações. | AC22: FAVORÁVEL | AD22: DANIEL DE PAULA GUIMARÃES | AE22: 1ª | AF22: 46077 | AG22: O acórdão foi plenamente favorável à Cargox, consolidando a improcedência da ação e confirmando a vitória da empresa em 1ª e 2ª instâncias. | AH22: N/A | AI22: N/A | AJ22: N/A | AK22: N/A | AL22: N/A | AM22: 91017.76 | AN22: 0 | AO22: 0 | AP22: 0 | AQ22: 0 | AR22: N/A | AS22: 0 | AT22: 0 | AU22: N/A | AV22: 0 | AW22: N/A | AX22: 46079 | AY22: Considerando que, após a publicação do acórdão, o reclamante não interpôs recurso de revista, operou-se o trânsito em julgado e os autos retornaram à Vara de origem, onde permanecem aguardando o arquivamento.
A23: 45817 | B23: 2 | C23: 1001267-10.2025.5.02.0203 | D23: DIMITRI FERREIRA DE PAULA E SILVA | E23: PIMENTEL ADVOGADA | F23: FRETEBRAS INTERNET E SERVIÇOS LTDA | G23: N/A | H23: TRABALHISTA | I23: EX-EMPREGADO | J23: ANALISTA COMERCIAL I | K23: RECURSAL | L23: AGUARDANDO INTERPOSIÇÃO DE RECURSO | M23: PROVÁVEL | N23: 3ª VARA DO TRABALHO DE BARUERI | O23: 2ª | P23: BARUERI/SP | Q23: Comissões R$ 27.832,09; Horas extras R$ 59.494,81; Intervalo intrajornada R$ 13.770,36; Multa do art. 477 da CLT R$ 2.600,34; FGTS R$ 8.667,70; Multa de 40% do FGTS R$ 3.249,55; Multa do art. 467 da CLT R$ 1.624,77; Doença ocupacional; Honorários de sucumbência e Gratuidade de justiça. | R23: A audiência trouxe contradições relevantes entre os depoimentos, especialmente sobre jornada, metas e uso de recursos da empresa. A defesa da Fretebras pode sustentar que o reclamante atuava em regime remoto, com metas específicas, sem controle de jornada, o que afasta pedidos de horas extras e reforça a tese empresarial. | S23: 46000 | T23: AMANDA CRISTINA DA SILVA | U23: THASSIA COSTA DA LUZ | V23: IVAN DE SOUSA AMORIM | W23: DOENÇA - DESFAVORÁVEL | X23: THALITA RUSSO DOMENICH | Y23: DESFAVORÁVEL | Z23: TÂMARA LUIZA VIEIRA RASIA | AA23: 46057 | AB23: A sentença foi parcialmente favorável à Fretebras, pois afastou multas e limitou valores da condenação, mas manteve condenações significativas em horas extras, diferenças de DSR e indenização por doença ocupacional. | AC23: DESFAVORÁVEL | AD23: MOISES DOS SANTOS HEITOR | AE23: 1ª | AF23: 46135 | AG23: O acórdão confirma parcialmente direitos do reclamante (como horas extras e estabilidade acidentária), mas também acolhe parcialmente pedidos da reclamada (redução de honorários e revisão sobre DSR). | AH23: N/A | AI23: N/A | AJ23: N/A | AK23: N/A | AL23: N/A | AM23: 149091.42 | AN23: 50000 | AO23: 0 | AP23: 0 | AQ23: 0 | AR23: N/A | AS23: 13813.83 | AT23: 0 | AU23: N/A | AV23: 0 | AW23: N/A | AX23: 46135 | AY23: Atualmente, o processo aguarda julgamento do recurso ordinário interposto pela reclamada, o qual já foi regularmente distribuído no âmbito do TRT. Foi proferido acórdão que deu parcial provimento aos recursos interpostos pela reclamada e pelo reclamante. No momento, o processo aguarda eventual oposição de embargos de declaração ou a interposição de recurso de revista pelas partes.
A24: 45834 | B24: 2 | C24: 1001038-32.2025.5.02.0015 | D24: CICERO RAMON SANTOS ALVES | E24: RODRIGUES & MIRANDA ADVOGADOS ASSOCIADOS | F24: FRETEBRAS INTERNET E SERVIÇOS LTDA | G24: N/A | H24: TRABALHISTA | I24: EX-EMPREGADO | J24: ANALISTA COMERCIAL III | K24: CONHECIMENTO | L24: AGUARDANDO MANIFESTAÇÃO | M24: PROVÁVEL | N24: 15ª VARA DO TRABALHO DE SÃO PAULO | O24: 1ª | P24: SÃO PAULO/SP | Q24: Cumprimento de sentença | R24: A audiência teve como objetivo a tentativa de conciliação entre as partes, contudo restou infrutífera. | S24: 46001 | T24: LETICIA DARC SILVA SATURNINO | U24: N/A | V24: N/A | W24: NÃO HÁ PEDIDO | X24: N/A | Y24: N/A | Z24: N/A | AA24: N/A | AB24: N/A | AC24: N/A | AD24: N/A | AE24: N/A | AF24: N/A | AG24: N/A | AH24: N/A | AI24: N/A | AJ24: N/A | AK24: N/A | AL24: N/A | AM24: 52552.02 | AN24: 135000 | AO24: 67727.72 | AP24: 0 | AQ24: 0 | AR24: N/A | AS24: 20,.902,45 | AT24: 68441.11 | AU24: RECLAMANTE | AV24: 0 | AW24: N/A | AX24: 46126 | AY24: Processo aguarda trânsito em julgado dos autos principais. O reclamante apresentou manifestação nos autos, requerendo a intimação da reclamada.
A25: 45853 | B25: 2 | C25: 1001141-26.2025.5.02.0084 | D25: SOPHYA SECCHIERO LISBOA | E25: RODRIGUES & MIRANDA ADVOGADOS ASSOCIADOS | F25: FRETEBRAS INTERNET E SERVIÇOS LTDA | G25: N/A | H25: TRABALHISTA | I25: EX-EMPREGADO | J25: ANALISTA COMERCIAL I | K25: RECURSAL | L25: AGUARDANDO JULGAMENTO DO RECURSO ORDINÁRIO | M25: POSSÍVEL | N25: 84ª VARA DO TRABALHO DE SÃO PAULO | O25: 2ª | P25: SÃO PAULO/SP | Q25: Verbas rescisórias R$ 20.279,00; FGTS R$ 15.047,00; Multa de 40% do FGTS R$ 6.019,00; Seguro desemprego R$ 8.496,00; DSR R$ 12.400,00; Equiparação salarial R$ 41.799,00; Indenização por dano moral R$ 10.000,00; Doença profissional R$ 20.000,00; Honorários de sucumbência R$ 13.404,00 e Gratuidade de justiça. | R25: A audiência trouxe elementos que fortalecem a defesa da Fretebras, especialmente na questão da equiparação salarial (diferença de complexidade das carteiras) e na alegação de dano moral (existência de canal de denúncia e ausência de provas robustas). | S25: 45908 | T25: KARINA VALENTIM GINDERO | U25: N/A | V25: GRAZIELA SOUZA GOMES | W25: DOENÇA - FAVORÁVEL | X25: GIANE MIRANDA RODRIGUES DA SILVA | Y25: DESFAVORÁVEL | Z25: TALITA LUCI MENDES FALCAO | AA25: 45912 | AB25: A sentença foi parcialmente favorável à Fretebras, pois afastou pedidos de maior impacto (doença ocupacional, danos morais e reversão da justa causa), mas manteve condenações relevantes em DSR sobre comissões e equiparação salarial. | AC25: AGUARDANDO | AD25: VALERIA NICOLAU SANCHEZ | AE25: 2º | AF25: N/A | AG25: N/A | AH25: N/A | AI25: N/A | AJ25: N/A | AK25: N/A | AL25: N/A | AM25: 147444 | AN25: 50000 | AO25: 0 | AP25: 0 | AQ25: 0 | AR25: N/A | AS25: 13133.46 | AT25: 0 | AU25: N/A | AV25: 0 | AW25: N/A | AX25: 46129 | AY25: Atualmente, o processo aguarda julgamento do recurso ordinário interposto pela reclamada, o qual já foi regularmente distribuído no âmbito do TRT.
A26: 45855 | B26: 3 | C26: 0010933-35.2025.5.03.0038 | D26: MARIANA ZIBORDI PELEGRINI | E26: SALLES & CARVALHO ADVOGADOS | F26: FRETEBRAS INTERNET E SERVIÇOS LTDA | G26: N/A | H26: TRABALHISTA | I26: EX-EMPREGADO | J26: ESPECIALISTA DE MARKETING | K26: CONHECIMENTO | L26: AGUARDANDO AUDIÊNCIA | M26: POSSÍVEL | N26: 4ª VARA DO TRABALHO DE JUIZ DE FORA | O26: 1ª | P26: JUIZ DE FORA/MG | Q26: Salários vencidos R$ 30.000,00; Rescisão indireta; Verbas rescisórias R$ 30.000,00; Garantia de emprego R$ 30.000,00; Indenização por dano moral R$ 30.000,00; Honorários de sucumbência R$ 18.000,00 e Gratuidade de justiça. | R26: N/A | S26: N/A | T26: N/A | U26: N/A | V26: N/A | W26: DOENÇA - FAVORÁVEL | X26: JOSÉ AUGUSTO DUARTE NETO | Y26: AGUARDANDO | Z26: N/A | AA26: N/A | AB26: N/A | AC26: N/A | AD26: N/A | AE26: N/A | AF26: N/A | AG26: N/A | AH26: N/A | AI26: N/A | AJ26: N/A | AK26: N/A | AL26: N/A | AM26: 138000 | AN26: 0 | AO26: 0 | AP26: 0 | AQ26: 0 | AR26: N/A | AS26: 0 | AT26: 0 | AU26: N/A | AV26: 0 | AW26: N/A | AX26: 46105 | AY26: Aguardando a audiência de instrução designada para o dia 05/05/2026, às 13h10.
A27: 45881 | B27: 2 | C27: 1001409-15.2025.5.02.0720 | D27: NATHANY LOUISY DE OLIVEIRA | E27: KNIJNIK & ZIPPIN ADVOGADOS ASSOCIADOS | F27: CARGOX AGENCIADORA DE SERVIÇOS E CARGAS LTDA | G27: N/A | H27: TRABALHISTA | I27: EX-EMPREGADO | J27: COORDENADOR DE OPERACOES | K27: EXECUÇÃO | L27: AGUARDANDO JULGAMENTO DO RECURSO ORDINÁRIO | M27: POSSÍVEL | N27: 20ª VARA DO TRABALHO DE SÃO PAULO - ZONA SUL | O27: 1ª | P27: SÃO PAULO/SP | Q27: Horas extras R$ 105.853,44; Intervalo intrajornada R$ 16.567,20; Intervalo interjornada R$ 13.567,12; Feriados R$ 16.112,56; Indenização por dano moral R$ 10.000,00; Honorários de sucumbência R$ 16.207,03 e Gratuidade de justiça. | R27: A audiência foi conduzida de forma equilibrada, com ambas as partes apresentando testemunhas. A Cargox conseguiu reforçar sua tese defensiva sobre jornada e condições de trabalho, e agora aguarda julgamento marcado para outubro. | S27: 45929 | T27: KARINA VALENTIM GINDERO | U27: CAMILA VELASCO DE GODOY; LARISSA BARBOSA DE ABREU | V27: RAFAEL RODRIGUES; DIEGO CAMARGO SILVA; MAYARA SAMPAIO SANTANA | W27: NÃO HÁ PEDIDO | X27: N/A | Y27: FAVORÁVEL | Z27: FERNANDO MAIDANA MIGUEL | AA27: 45946 | AB27: A sentença foi majoritariamente favorável à reclamada, pois reconheceu o exercício de cargo de confiança, afastou horas extras e aplicou prescrição quinquenal. As condenações foram limitadas, mantendo a defesa da empresa sólida. | AC27: DESFAVORÁVEL | AD27: FERNANDO CESAR TEIXEIRA FRANÇA | AE27: 6ª | AF27: 46101 | AG27: O acórdão foi desfavorável à reclamada, pois anulou a sentença que havia rejeitado os pedidos da reclamante, determinando nova audiência para ouvir a preposta da empresa. Isso reabre a discussão sobre jornada e cargo de confiança, pontos centrais da defesa | AH27: N/A | AI27: N/A | AJ27: N/A | AK27: N/A | AL27: N/A | AM27: 162070.32 | AN27: 0 | AO27: 0 | AP27: 0 | AQ27: 0 | AR27: N/A | AS27: 0 | AT27: 0 | AU27: N/A | AV27: 0 | AW27: N/A | AX27: 46093 | AY27: Atualmente, o processo aguarda julgamento do recurso ordinário interposto pela reclamante, o qual já foi regularmente distribuído no âmbito do TRT.
A28: 45894 | B28: 2 | C28: 1001427-86.2025.5.02.0089 | D28: DIOGO BARBOSA SOARES | E28: FONTANA | F28: FRETEBRAS INTERNET E SERVIÇOS LTDA | G28: N/A | H28: TRABALHISTA | I28: EX-EMPREGADO | J28: COORDENADOR COMERCIAL | K28: EXECUÇÃO | L28: AGUARDANDO LIBERAÇÃO DO VALOR DEPOSITADO | M28: PROVÁVEL | N28: 89ª VARA DO TRABALHO DE SÃO PAULO | O28: 1ª | P28: SÃO PAULO/SP | Q28: DSR’s R$ 61.927,72; Comissões R$ 22.568,22; Indenização por dano moral R$ 58.441,55; Honorários de sucumbência e Gratuidade de justiça. | R28: Considerando que os pedidos formulados pelo reclamante estão amparados em prova documental, foi dispensada a colheita dos depoimentos pessoais. | S28: 45951 | T28: MANDA CRISTINA DA SILVA | U28: N/A | V28: N/A | W28: NÃO HÁ PEDIDO | X28: N/A | Y28: DESFAVORÁVEL | Z28: MARCELO PEREIRA DAS NEVES | AA28: 45972 | AB28: A sentença foi parcialmente desfavorável à Fretebras, com condenação em DSR e reflexos, mas a empresa obteve êxito em afastar pedidos de maior impacto financeiro, como danos morais e diferenças de comissões. | AC28: N/A | AD28: N/A | AE28: N/A | AF28: N/A | AG28: N/A | AH28: N/A | AI28: N/A | AJ28: N/A | AK28: N/A | AL28: N/A | AM28: 169485.28 | AN28: 50000 | AO28: 129336.65 | AP28: 43818.21 | AQ28: 0 | AR28: N/A | AS28: 45664.26 | AT28: 46677.92 | AU28: RECLAMADA | AV28: 85518.44 | AW28: N/A | AX28: 46127 | AY28: Em decisão de homologação, foram acolhidos os cálculos apresentados pela reclamada. Assim, a empresa foi intimada para garantir o juízo no prazo de 15 dias. Foi apresentado o comprovante de pagamento da execução.
A29: 45900 | B29: 4 | C29: 0020538-28.2025.5.04.0571 | D29: ERLI SCHMIDT | E29: CALLIARI & TEIXEIRA ADVOGADOS ASSOCIADOS | F29: FRETEBRAS INTERNET E SERVIÇOS LTDA | G29: N/A | H29: TRABALHISTA | I29: EX-EMPREGADO | J29: MOTORISTA | K29: RECURSAL | L29: AGUARDANDO JULGAMENTO DO RECURSO ORDINÁRIO | M29: REMOTO | N29: VARA DO TRABALHO DE SOLEDADE | O29: 2ª | P29: SOLEDADE/RS | Q29: Indenização por dano moral R$ 20.000,00; Honorários de sucumbência R$ 2.000,00 e Gratuidade de justiça. | R29: Foi realizada a oitiva das partes, registrada por meio de degravação. | S29: 45993 | T29: ODAIR JOSE LUCIANI | U29: N/A | V29: N/A | W29: NÃO HÁ PEDIDO | X29: N/A | Y29: FAVORÁVEL | Z29: VINICIUS DANIEL PETRY | AA29: 46037 | AB29: Ficou reconhecido que a Fretebras agiu dentro da legalidade, não houve dano moral, nem obrigação de reativar conta ou expedir documentos. | AC29: AGUARDANDO | AD29: RICARDO CARVALHO FRAGA | AE29: 3ª | AF29: N/A | AG29: N/A | AH29: N/A | AI29: N/A | AJ29: N/A | AK29: N/A | AL29: N/A | AM29: R$ 22.000,00 | AN29: 0 | AO29: 0 | AP29: 0 | AQ29: 0 | AR29: N/A | AS29: 0 | AT29: 0 | AU29: N/A | AV29: 0 | AW29: N/A | AX29: 46099 | AY29: Certidão de distribuição emitida pelo TRT, indicando que o processo aguarda julgamento do recurso ordinário interposto pelo reclamante.
A30: 45901 | B30: 24 | C30: 0025413-32.2025.5.24.0006 | D30: FELIPE WESLLEY BARBOSA DA SILVA | E30: JOCIANDO ALVES ADVOCACIA | F30: INTERSITE SISTEMAS LTDA. | G30: N/A | H30: TRABALHISTA | I30: EX-EMPREGADO | J30: TÉCNICO DE SUPORTE II | K30: CONHECIMENTO | L30: AGUARDANDO INTERPOSIÇÃO DE RECURSO | M30: POSSÍVEL | N30: 6ª VARA DO TRABALHO DE CAMPO GRANDE | O30: 1ª | P30: CAMPO GRANDE/MS | Q30: Diferenças salariais R$ 9.961,64; Multa prevista na CCT R$ 2.113,17; Multa do art. 477 da CLT R$ 3.146,01; Indenização por dano moral R$ 3.146,01; Honorários de sucumbência e Gratuidade de justiça. | R30: As partes permaneceram inconciliadas, tendo sido realizada a oitiva das partes e da testemunha da reclamada, por meio de degravação. | S30: 46091 | T30: KARINA VALENTIM GINDERO | U30: RICARDO CAMPEAO DE MORAES | V30: N/A | W30: NÃO HÁ PEDIDO | X30: N/A | Y30: DESFAVORÁVEL | Z30: GUSTAVO DORETO RODRIGUES | AA30: 46132 | AB30: aempresa foi condenada a pagar diferenças salariais, FGTS, indenização por danos morais e multas convencionais, os demais pedidos do autor foram indeferidos. | AC30: N/A | AD30: N/A | AE30: N/A | AF30: N/A | AG30: N/A | AH30: N/A | AI30: N/A | AJ30: N/A | AK30: N/A | AL30: N/A | AM30: 18366.83 | AN30: 14000 | AO30: 0 | AP30: 0 | AQ30: 0 | AR30: N/A | AS30: 0 | AT30: 0 | AU30: N/A | AV30: 0 | AW30: N/A | AX30: 46132 | AY30: Concluída a audiência de instrução, o feito aguarda, neste momento, a prolação da sentença. Diante da decisão proferida nos autos, permanece a expectativa quanto à eventual oposição de embargos de declaração ou à interposição de recurso ordinário.
A31: 45911 | B31: 2 | C31: 1001544-72.2025.5.02.0026 | D31: DIEGO OLIVA GOMES | E31: ADVOCACIA TRABALHISTA TOFOLI | F31: FRETEBRAS INTERNET E SERVIÇOS LTDA | G31: N/A | H31: TRABALHISTA | I31: EX-EMPREGADO | J31: ASSISTENTE DE ATENDIMENTO N1 | K31: CONHECIMENTO | L31: AGUARDANDO SENTENÇA | M31: POSSÍVEL | N31: 26ª VARA DO TRABALHO DE SÃO PAULO | O31: 1ª | P31: SÃO PAULO/SP | Q31: Verbas rescisórias R$ 4.492,43; Horas extras R$ 12.701,98; Adicional noturno R$ 3.838,87; Multa de 40% do FGTS R$ 950,84; FGTS R$ 1.452,11; Multa do art. 477 da CLT R$ 2.606,63; Multa normativa R$ 182,50; Seguro desemprego R$ 8.589,64; Indenização por dano moral R$ 30.000,00; Multa do art. 467 da CLT R$ 3.146,12; Honorários de sucumbência R$ 10.194,17 e Gratuidade de justiça. | R31: Depoimento do reclamante: afirma ter sido dispensado por justa causa sem motivo específico informado; trabalhava em home office, registrava jornada corretamente, recebeu advertências e suspensões, não retornou ao presencial por necessidade de cuidar do filho, comparecendo apenas no dia da demissão. Depoimento do preposto da reclamada: alega justa causa por desídia, mau procedimento e indisciplina; reclamante não retornou ao trabalho presencial após convocação em março de 2025, comparecendo apenas no desligamento em julho; controle de jornada era feito via sistema. Testemunha da reclamada: confirma histórico de faltas disciplinares, advertências e descumprimento da determinação de retorno presencial; cartões de ponto refletiam a realidade. | S31: 46134 | T31: KARINA VALENTIM GINDERO | U31: PAULA NAYANE SILVESTRE MITHERHOFER | V31: N/A | W31: NÃO HÁ PEDIDO | X31: N/A | Y31: N/A | Z31: N/A | AA31: N/A | AB31: N/A | AC31: N/A | AD31: N/A | AE31: N/A | AF31: N/A | AG31: N/A | AH31: N/A | AI31: N/A | AJ31: N/A | AK31: N/A | AL31: N/A | AM31: 67961.14 | AN31: 0 | AO31: 0 | AP31: 0 | AQ31: 0 | AR31: N/A | AS31: 0 | AT31: 0 | AU31: N/A | AV31: 0 | AW31: N/A | AX31: 46134 | AY31: Após a apresentação da réplica pelo reclamante, os autos permanecem aguardando a audiência de instrução, já designada para o dia 22/04/2026, às 14h45. Audiência de instrução realizada, com julgamento designado para o dia 13/05/2026 às 16h04, aguardando-se a prolação da sentença.
A32: 45963 | B32: 4 | C32: 0030241-47.2025.5.04.0000 | D32: ERLI SCHMIDT | E32: CALLIARI & TEIXEIRA ADVOGADOS ASSOCIADOS | F32: FRETEBRAS INTERNET E SERVIÇOS LTDA | G32: MAGISTRADO DA VARA DO TRABALHO DE CARAZINHO | H32: TRABALHISTA | I32: EX-EMPREGADO | J32: MOTORISTA | K32: RECURSAL | L32: AGUARDANDO ARQUIVAMENTO | M32: REMOTO | N32: 1ª SDI | O32: 2ª | P32: SOLEDADE/RS | Q32: O reclamante alegou que teve sua conta desativada definitivamente na plataforma da Fretebras, sem justificativa concreta, o que estaria impedindo o exercício da sua profissão de motorista de cargas. Sustentou que a decisão que negou a tutela de urgência (que buscava o desbloqueio imediato da conta) violou seu direito líquido e certo ao trabalho, à dignidade e à honra, pois o bloqueio o impossibilita de obter o seguro obrigatório e, consequentemente, de ser contratado por transportadoras. Como não há recurso próprio para atacar decisão interlocutória que indefere tutela provisória, o reclamante utilizou o Mandado de Segurança como meio adequado para tentar suspender o ato e garantir o restabelecimento do cadastro. | R32: N/A | S32: N/A | T32: N/A | U32: N/A | V32: N/A | W32: NÃO HÁ PEDIDO | X32: N/A | Y32: N/A | Z32: N/A | AA32: N/A | AB32: N/A | AC32: FAVORÁVEL | AD32: ANGELA ROSI ALMEIDA CHAPPER | AE32: 1ª | AF32: 46008 | AG32: O Tribunal reconheceu que não houve ilegalidade ou abusividade na decisão que indeferiu a liminar. Ficou afastada a tese de bloqueio arbitrário e de violação a direito líquido e certo. O mandado de segurança foi integralmente rejeitado, mantendo a empresa livre de qualquer obrigação imediata de reativar cadastro ou excluir registros. | AH32: N/A | AI32: N/A | AJ32: N/A | AK32: N/A | AL32: N/A | AM32: 1000 | AN32: 0 | AO32: 0 | AP32: 0 | AQ32: 0 | AR32: N/A | AS32: 0 | AT32: 0 | AU32: N/A | AV32: 0 | AW32: N/A | AX32: 46073 | AY32: O impetrante foi intimado a efetuar o pagamento das custas processuais e, após a quitação, será determinado o arquivamento dos autos.
A33: 46052 | B33: 2 | C33: 1000134-68.2026.5.02.0082 | D33: GUTENBERG DE OLIVEIRA | E33: LIMA ADVOGADOS ASSOCIADOS | F33: FRETEBRAS INTERNET E SERVIÇOS LTDA | G33: N/A | H33: TRABALHISTA | I33: EX-EMPREGADO | J33: ANALISTA COMERCIAL II | K33: CONHECIMENTO | L33: AGUARDANDO ARQUIVAMENTO | M33: REMOTO | N33: 82ª VARA DO TRABALHO DE SÃO PAULO | O33: 1ª | P33: SÃO PAULO/SP | Q33: Horas extras R$ 57.757,55; Comissões R$ 95.576,04; DSR R$ 25.269,30; Integrações de valores pagos R$ 15.260,30; Verbas rescisórias R$ 26.450,65; Contribuição assistencial R$ 2.615,44; Multa do art. 477 da CLT R$ 5.900,00; Indenização por dano moral R$ 30.000,00; Honorários de sucumbência e Gratuidade de justiça. | R33: N/A | S33: N/A | T33: N/A | U33: N/A | V33: N/A | W33: NÃO HÁ PEDIDO | X33: N/A | Y33: N/A | Z33: N/A | AA33: N/A | AB33: N/A | AC33: N/A | AD33: N/A | AE33: N/A | AF33: N/A | AG33: N/A | AH33: N/A | AI33: N/A | AJ33: N/A | AK33: N/A | AL33: N/A | AM33: 258829.28 | AN33: 0 | AO33: 0 | AP33: 0 | AQ33: 0 | AR33: N/A | AS33: 0 | AT33: 0 | AU33: N/A | AV33: 0 | AW33: N/A | AX33: 46111 | AY33: Tendo em vista a desistência do reclamante, foi determinada a extinção do processo sem resolução do mérito, com consequente arquivamento dos autos.
A34: 46070 | B34: 2 | C34: 1000221-27.2026.5.02.0081 | D34: FELIPE CARDOSO DE BRITO | E34: ZAMITH ASSESSORIA JURÍDICA | F34: FRETEBRAS INTERNET E SERVIÇOS LTDA | G34: N/A | H34: TRABALHISTA | I34: EX-EMPREGADO | J34: COORDENADOR DE VENDAS | K34: CONHECIMENTO | L34: AGUARDANDO SENTENÇA | M34: POSSÍVEL | N34: 81ª VARA DO TRABALHO DE SÃO PAULO | O34: 1ª | P34: SÃO PAULO/SP | Q34: DSR R$ 133.044,54; FGTS R$ 36.834,37; Multa de 40% do FGTS R$ 14.733,75; Descaracterização do valores nomeados como "Comissões DSR"; Honorários de sucumbência e Gratuidade de justiça. | R34: Depoimento do reclamante: afirmou que a empresa não pagava corretamente os DSRs sobre as comissões. Segundo ele, o valor indicado como DSR no holerite era apenas parte da comissão já devida, e não um adicional. Declarou que mensalmente recebia planilhas em Excel com os valores de comissão, mas nunca havia visto o documento exibido em audiência. Depoimento da reclamada: explicou que o cálculo do DSR era feito dividindo a comissão pelos dias úteis e multiplicando por domingos e feriados. Apresentou documento oficial da empresa, esclarecendo que se tratava de uma projeção dos ganhos totais do colaborador. | S34: 46134 | T34: KARINA VALENTIM GINDERO | U34: N/A | V34: N/A | W34: NÃO HÁ PEDIDO | X34: N/A | Y34: N/A | Z34: N/A | AA34: N/A | AB34: N/A | AC34: N/A | AD34: N/A | AE34: N/A | AF34: N/A | AG34: N/A | AH34: N/A | AI34: N/A | AJ34: N/A | AK34: N/A | AL34: N/A | AM34: 184612.66 | AN34: 0 | AO34: 0 | AP34: 0 | AQ34: 0 | AR34: N/A | AS34: 0 | AT34: 0 | AU34: N/A | AV34: 0 | AW34: N/A | AX34: 46134 | AY34: Aguardando a audiência de UNA designada para o dia 22/04/2026, às 10h20. Audiência de instrução realizada, com julgamento designado para o dia 15/05/2026 às 18h23, aguardando-se a prolação da sentença.
A35: 46105 | B35: 12 | C35: 0000296-42.2026.5.12.0037 | D35: EDGAR EL HAGE THOMPSON NETO | E35: ALBUQUERQUE AQUINO ADVOCACIA | F35: FRETEBRAS INTERNET E SERVIÇOS LTDA | G35: N/A | H35: TRABALHISTA | I35: EX-EMPREGADO | J35: EXECUTIVO PLENO | K35: CONHECIMENTO | L35: AGUARDANDO AUDIÊNCIA | M35: POSSÍVEL | N35: 7ª VARA DO TRABALHO DE FLORIANÓPOLIS | O35: 1ª | P35: FLORIANÓPOLIS/SC | Q35: Retificação da CTPS; Equiparação salarial R$ 90.197,33; FGTS R$ 6.720,00; Verbas rescisórias R$ 18.252,13; Indenização por dano moral R$ 20.000,00; Honorários de sucumbência e Gratuidade de justiça. | R35: N/A | S35: N/A | T35: N/A | U35: N/A | V35: N/A | W35: NÃO HÁ PEDIDO | X35: N/A | Y35: N/A | Z35: N/A | AA35: N/A | AB35: N/A | AC35: N/A | AD35: N/A | AE35: N/A | AF35: N/A | AG35: N/A | AH35: N/A | AI35: N/A | AJ35: N/A | AK35: N/A | AL35: N/A | AM35: 135169.46 | AN35: 0 | AO35: 0 | AP35: 0 | AQ35: 0 | AR35: N/A | AS35: 0 | AT35: 0 | AU35: N/A | AV35: 0 | AW35: N/A | AX35: 46119 | AY35: Aguardando a audiência de Conciliação designada para o dia 09/06/2026, às 14h10.
A36: 46080 | B36: 2 | C36: 1000294-87.2026.5.02.0084 | D36: SOPHYA SECCHIERO LISBOA | E36: RODRIGUES & MIRANDA ADVOGADOS ASSOCIADOS | F36: FRETEBRAS INTERNET E SERVIÇOS LTDA | G36: N/A | H36: TRABALHISTA | I36: EX-EMPREGADO | J36: ANALISTA COMERCIAL I | K36: EXECUÇÃO | L36: AGUARDANDO MANIFESTAÇÃO | M36: PROVÁVEL | N36: 84ª VARA DO TRABALHO DE SÃO PAULO | O36: 1ª | P36: SÃO PAULO/SP | Q36: Cumprimento de sentença | R36: N/A | S36: N/A | T36: N/A | U36: N/A | V36: N/A | W36: NÃO HÁ PEDIDO | X36: N/A | Y36: N/A | Z36: N/A | AA36: N/A | AB36: N/A | AC36: N/A | AD36: N/A | AE36: N/A | AF36: N/A | AG36: N/A | AH36: N/A | AI36: N/A | AJ36: N/A | AK36: N/A | AL36: N/A | AM36: 38734.36 | AN36: 0 | AO36: 36606.79 | AP36: 63924.19 | AQ36: 0 | AR36: N/A | AS36: 0 | AT36: 0 | AU36: N/A | AV36: 27317.4 | AW36: N/A | AX36: 46118 | AY36: O reclamante apresentou manifestação nos autos, impugnando os cálculos por nós apresentados.

Sheet ENCERRADOS
A1: PROCESSOS ENCERRADOS - ABRIL/2026
A2: TRT | B2: NÚMERO DO PROCESSO | C2: PARTE CONTRÁRIA | D2: DATA DO ENCERRAMENTO | E2: MOTIVO DO ENCERRAMENTO | F2: VALORES PAGOS
A3: 2 | B3: 1000686-22.2019.5.02.0068 | C3: LUDMILA COELHO FABRICIO DA SILVA | D3: 43671 | E3: ACORDO ENTRE AS PARTES | F3: 30000
A4: 15 | B4: 0010413-63.2019.5.15.0002 | C4: EDSON BASTOS CORREIA | D4: 43696 | E4: EXCEÇÃO DE INCOMPETÊNCIA | F4: 0
A5: 2 | B5: 1000774-19.2019.5.02.0211 | C5: EDSON BASTOS CORREIA | D5: 43699 | E5: FALTA DE INDICAÇÃO DO ENDEREÇO DA 1ª RÉ | F5: 0
A6: 2 | B6: 1000889-40.2019.5.02.0211 | C6: EDSON BASTOS CORREIA | D6: 44018 | E6: ACORDO ENTRE AS PARTES | F6: 8000
A7: 2 | B7: 1000583-86.2020.5.02.0033 | C7: CINTIA REGINA DA CRUZ DE SOUZA | D7: 44047 | E7: ACORDO ENTRE AS PARTES | F7: 5000
A8: 2 | B8: 1001199-24.2019.5.02.0089 | C8: KAREN REGINA RODRIGUES | D8: 44082 | E8: EXECUÇÃO FINALIZADA | F8: 1701.7
A9: 2 | B9: 1001105-39.2019.5.02.0069 | C9: DANIEL RIBEIRO DA SILVA | D9: 44319 | E9: ACORDO ENTRE AS PARTES | F9: 50000
A10: 3 | B10: 0010768-45.2021.5.03.0032 | C10: ANA LUIZA OLIVEIRA DINIZ | D10: 44516 | E10: DESISTÊNCIA DA AÇÃO | F10: 0
A11: 15 | B11: 0010165-26.2020.5.15.0079 | C11: HUGO VOLTOLINO LOMBARDI DE SOUZA | D11: 44671 | E11: ACORDO ENTRE AS PARTES | F11: 32400
A12: 15 | B12: 0012325-98.2018.5.15.0077 | C12: ERICK GOMES DOS SANTOS | D12: 44792 | E12: EXECUÇÃO FINALIZADA | F12: 1470.34
A13: 2 | B13: 1000227-95.2022.5.02.0009 | C13: GABRIELA PEREIRA LOPES | D13: 44986 | E13: EXECUÇÃO FINALIZADA | F13: 1477.14
A14: 2 | B14: 1000276-70.2021.5.02.0010 | C14: LUCAS SANTANA DE SOUZA | D14: 45013 | E14: ACORDO ENTRE AS PARTES | F14: 0
... A67: 3 | B67: 0010838-23.2025.5.03.0129 | C67: MATHEUS RAFAEL DE SOUZA SILVA | D67: 46056 | E67: DESISTÊNCIA DA AÇÃO EM FASE DA FRETE | F67: 0

Sheet PROCEDIMENTO ADMINISTRATIVO
A1: PROCEDIMENTO ADMINISTRATIVO - ABRIL/2026
A2: Data da distribuição | B2: Número do processo | C2: Ação | D2: Cliente principal | E2: Contrário principal | F2: Cidade | G2: UF | H2: Motivo | I2: Status
A3: 44637 | B3: 14152.037968/2022-86 | C3: Notificação administrativa | D3: FRETEBRAS INTERNET E SERVIÇOS LTDA | E3: MINISTÉRIO DO TRABALHO E PREVIDÊNCIA | F3: Goiânia | G3: GO | H3: Autuado por deixar de apresentar documentos sujeitos à inspeção do trabalho no dia e hora previamente fixados pelo AFT. | I3: Arquivado
A4: 44637 | B4: 14152.037962/2022-17 | C4: Notificação administrativa | D4: FRETEBRAS INTERNET E SERVIÇOS LTDA | E4: MINISTÉRIO DO TRABALHO E PREVIDÊNCIA | F4: Goiânia | G4: GO | H4: Autuado por deixar de empregar aprendizes em número equivalente a 5% (cinco por cento), no mínimo, dos empregados existentes em cada estabelecimento, cujas funções demandem formação profissional. | I4: Arquivado
A5: 44651 | B5: 3658/2022 | C5: Notificação administrativa | D5: FRETEBRAS INTERNET E SERVIÇOS LTDA | E5: MINISTÉRIO DO TRABALHO E PREVIDÊNCIA | F5: Goiânia | G5: GO | H5: Não preenchimento de cota (PCD) | I5: APRESENTAMOS DEFESA - ASSINAMOS TERMO DE COMPROMISSO DE ADEQUAÇÃO DA COTA (PCD).

Sheet _ChartData
A1: Instância | B1: Favorável | C1: Desfavorável
A2: 1º Grau | B2: =COUNTIF(ATIVOS!Y3:Y908,"FAVORÁVEL") -> 4 | C2: =COUNTIF(ATIVOS!Y3:Y908,"DESFAVORÁVEL") -> 18
A3: 2º Grau | B3: =COUNTIF(ATIVOS!AC3:AC908,"FAVORÁVEL") -> 7 | C3: =COUNTIF(ATIVOS!AC3:AC908,"DESFAVORÁVEL") -> 11
A4: TST | B4: =COUNTIF(ATIVOS!AH3:AH908,"FAVORÁVEL") -> 3 | C4: =COUNTIF(ATIVOS!AH3:AH908,"DESFAVORÁVEL") -> 1
A7: Status | B7: Qtd
A8: Improcedência | B8: =COUNTIF(ENCERRADOS!E3:E896,"IMPROCEDÊNCIA") -> 6
A9: Extinção/Outros | B9: =COUNTIF(ENCERRADOS!E3:E896,"AUSÊNCIA DO RECLAMANTE EM AUDIÊNCIA")+COUNTIF(ENCERRADOS!E3:E896,"DESISTÊNCIA DA AÇÃO")+COUNTIF(ENCERRADOS!E3:E896,"INICIAL INDEFERIDA")+COUNTIF(ENCERRADOS!E3:E896,"RECLAMANTE DESCONHECE ESCRITÓRIO")+COUNTIF(ENCERRADOS!E3:E896,"TROCA DE PATROCÍNIO") -> 1
A10: Acordo | B10: =COUNTIF(ENCERRADOS!E3:E896,"ACORDO ENTRE AS PARTES") -> 17
A11: Em Andamento | B11: =COUNTA(ATIVOS!C3:C908) -> 34
A12: Condenação | B12: =COUNTIF(ENCERRADOS!E3:E896,"EXECUÇÃO FINALIZADA") -> 30
